{
  "meta": {
    "platform": "toutiao",
    "date": "2026-04-06T02:33:24.850269",
    "count": 20
  },
  "data": [
    {
      "id": "7625107205005475850",
      "title": "北洋水师水兵墓前放着中国航母模型",
      "cover": "https://p26-sign.toutiaoimg.com/tos-cn-i-qvj2lq49k0/307b8e76089445e3a4738d15c142aa6f~tplv-tt-shrink:960:540.jpeg?_iz=30575&from=sign_default&lk3s=8d617dac&x-expires=1778025600&x-signature=F4jO5R1YOLQIiHhBHlDAQxInqfM%3D",
      "timestamp": 7625107205005476000,
      "hot": 64981354,
      "url": "https://www.toutiao.com/trending/7625107205005475850/",
      "mobileUrl": "https://api.toutiaoapi.com/feoffline/amos_land/new/html/main/index.html?topic_id=7625107205005475850"
    },
    {
      "id": "7624336383088656390",
      "title": "赵心童夺2026斯诺克巡回锦标赛冠军",
      "cover": "https://p3-sign.toutiaoimg.com/tos-cn-i-qvj2lq49k0/c42a5fbcd70941d4acceb7a6f499a7cc~tplv-tt-shrink:960:540.jpeg?_iz=30575&from=sign_default&lk3s=8d617dac&x-expires=1778025600&x-signature=m%2FV1%2B8zZlTg2LTCpf%2F%2FpX9GWnmk%3D",
      "timestamp": 7624336383088656000,
      "hot": 58797560,
      "url": "https://www.toutiao.com/trending/7624336383088656390/",
      "mobileUrl": "https://api.toutiaoapi.com/feoffline/amos_land/new/html/main/index.html?topic_id=7624336383088656390"
    },
    {
      "id": "7625167509165113387",
      "title": "这锦绣河山 我们替您守护",
      "cover": "https://p3-sign.toutiaoimg.com/tos-cn-i-qvj2lq49k0/d2065af2fe3c43a7a8ef059ec6c4fa46~tplv-tt-shrink:960:540.jpeg?_iz=30575&from=sign_default&lk3s=8d617dac&x-expires=1778025600&x-signature=8E5c3cVlVz9pd%2BIAh%2FCHdQPOZuc%3D",
      "timestamp": 7625167509165113000,
      "hot": 53202232,
      "url": "https://www.toutiao.com/trending/7625167509165113387/",
      "mobileUrl": "https://api.toutiaoapi.com/feoffline/amos_land/new/html/main/index.html?topic_id=7625167509165113387"
    },
    {
      "id": "7624590040673419300",
      "title": "王楚钦孙颖莎顶峰相见自拍",
      "cover": "https://p3-sign.toutiaoimg.com/tos-cn-i-qvj2lq49k0/49101cb4da3340a09312a20058d50b5d~tplv-tt-shrink:960:540.jpeg?_iz=30575&from=sign_default&lk3s=8d617dac&x-expires=1778025600&x-signature=QBiJNRM9tEJT%2BhGR7AYryj4WFnY%3D",
      "timestamp": 7624590040673419000,
      "hot": 48139371,
      "url": "https://www.toutiao.com/trending/7624590040673419300/",
      "mobileUrl": "https://api.toutiaoapi.com/feoffline/amos_land/new/html/main/index.html?topic_id=7624590040673419300"
    },
    {
      "id": "7625146788546674751",
      "title": "5人并排骑摩托堵住整条路",
      "cover": "https://p26-sign.toutiaoimg.com/tos-cn-i-qvj2lq49k0/60c1304327c74638ab6a642cbb629f81~tplv-tt-shrink:960:540.jpeg?_iz=30575&from=sign_default&lk3s=8d617dac&x-expires=1778025600&x-signature=PPMA6h9ezHugX1dx9GPZqYsUuT4%3D",
      "timestamp": 7625146788546675000,
      "hot": 43558304,
      "url": "https://www.toutiao.com/trending/7625146788546674751/",
      "mobileUrl": "https://api.toutiaoapi.com/feoffline/amos_land/new/html/main/index.html?topic_id=7625146788546674751"
    },
    {
      "id": "7624688096940294180",
      "title": "伊朗披露美军营救行动细节：彻底失败",
      "cover": "https://p26-sign.toutiaoimg.com/tos-cn-i-qvj2lq49k0/554c30f4f8b44364bb27e1f4fbc4991b~tplv-tt-shrink:960:540.jpeg?_iz=30575&from=sign_default&lk3s=8d617dac&x-expires=1778025600&x-signature=kLqPl1T3nqfPP8Z043Uic4GJ%2FYA%3D",
      "timestamp": 7624688096940294000,
      "hot": 39413183,
      "url": "https://www.toutiao.com/trending/7624688096940294180/",
      "mobileUrl": "https://api.toutiaoapi.com/feoffline/amos_land/new/html/main/index.html?topic_id=7624688096940294180"
    },
    {
      "id": "7624932893793468426",
      "title": "张雪澄清“一个子儿都没有”言论",
      "cover": "https://p26-sign.toutiaoimg.com/top-static-files-outer/breaknews/bd3a892c-0931-4855-886e-16c309765245~tplv-tt-shrink:960:540.jpeg?_iz=30575&from=sign_default&lk3s=8d617dac&x-expires=1778025600&x-signature=gpVfdGICX3ZK7Uftnq8SpjjMPPo%3D",
      "timestamp": 7624932893793468000,
      "hot": 35662523,
      "url": "https://www.toutiao.com/trending/7624932893793468426/",
      "mobileUrl": "https://api.toutiaoapi.com/feoffline/amos_land/new/html/main/index.html?topic_id=7624932893793468426"
    },
    {
      "id": "7624686886321131044",
      "title": "王楚钦距大满贯只差奥运单打金牌",
      "cover": "https://p26-sign.toutiaoimg.com/tos-cn-i-qvj2lq49k0/82fb027d829c4cfdb25aeedf1fbb0c0b~tplv-tt-shrink:960:540.jpeg?_iz=30575&from=sign_default&lk3s=8d617dac&x-expires=1778025600&x-signature=14ZOGTip93IAOZ9TRaB3%2FeDi%2Bqc%3D",
      "timestamp": 7624686886321132000,
      "hot": 32268785,
      "url": "https://www.toutiao.com/trending/7624686886321131044/",
      "mobileUrl": "https://api.toutiaoapi.com/feoffline/amos_land/new/html/main/index.html?topic_id=7624686886321131044"
    },
    {
      "id": "7624806568248492086",
      "title": "湖人“三巨头”变41岁单核老头",
      "cover": "https://p3-sign.toutiaoimg.com/tos-cn-i-qvj2lq49k0/3cb6131865d341c58358f6ecb1f9c573~tplv-tt-shrink:960:540.jpeg?_iz=30575&from=sign_default&lk3s=8d617dac&x-expires=1778025600&x-signature=jGMrwwCmAueQJUM1UNhY%2FWuuAXA%3D",
      "timestamp": 7624806568248492000,
      "hot": 29198004,
      "url": "https://www.toutiao.com/trending/7624806568248492086/",
      "mobileUrl": "https://api.toutiaoapi.com/feoffline/amos_land/new/html/main/index.html?topic_id=7624806568248492086"
    },
    {
      "id": "7624732703728304179",
      "title": "今天是农历二月十九观音诞辰日",
      "cover": "https://p26-sign.toutiaoimg.com/tos-cn-i-qvj2lq49k0/35b0273e51ae43309d78e66beb4d4d32~tplv-tt-shrink:960:540.jpeg?_iz=30575&from=sign_default&lk3s=8d617dac&x-expires=1778025600&x-signature=7y9yl2B55RhnHyJg4i5jfIsgjt0%3D",
      "timestamp": 7624732703728304000,
      "hot": 26419447,
      "url": "https://www.toutiao.com/trending/7624732703728304179/",
      "mobileUrl": "https://api.toutiaoapi.com/feoffline/amos_land/new/html/main/index.html?topic_id=7624732703728304179"
    },
    {
      "id": "7624913839618097215",
      "title": "都江堰淘出800克狗头金？假的",
      "cover": "https://p3-sign.toutiaoimg.com/tos-cn-i-qvj2lq49k0/cb2bb47ce5ae41d38f38fb62bbd03668~tplv-tt-shrink:960:540.jpeg?_iz=30575&from=sign_default&lk3s=8d617dac&x-expires=1778025600&x-signature=%2BIFSCezNMKNoQrTe7OaNSvnGRf4%3D",
      "timestamp": 7624913839618097000,
      "hot": 23905304,
      "url": "https://www.toutiao.com/trending/7624913839618097215/",
      "mobileUrl": "https://api.toutiaoapi.com/feoffline/amos_land/new/html/main/index.html?topic_id=7624913839618097215"
    },
    {
      "id": "7624368282019561518",
      "title": "以色列宣布已停止所有对法国防采购",
      "cover": "https://p3-sign.toutiaoimg.com/tos-cn-i-qvj2lq49k0/7d90ce14334f4e279237b291b64ba079~tplv-tt-shrink:960:540.jpeg?_iz=30575&from=sign_default&lk3s=8d617dac&x-expires=1778025600&x-signature=UYTi3p18DcK0Qp4LsUF2TVkWhoE%3D",
      "timestamp": 7624368282019561000,
      "hot": 21630413,
      "url": "https://www.toutiao.com/trending/7624368282019561518/",
      "mobileUrl": "https://api.toutiaoapi.com/feoffline/amos_land/new/html/main/index.html?topic_id=7624368282019561518"
    },
    {
      "id": "7625453500595621385",
      "title": "伊朗警告美国或封锁曼德海峡反制",
      "cover": "https://p3-sign.toutiaoimg.com/mosaic-legacy/2b29000036f8405561443~tplv-tt-shrink:960:540.jpeg?_iz=30575&from=sign_default&lk3s=8d617dac&x-expires=1778025600&x-signature=g2QbVgnTLwesTJQ2DAIbpp13n%2Fw%3D",
      "timestamp": 7625453500595622000,
      "hot": 19572007,
      "url": "https://www.toutiao.com/trending/7625453500595621385/",
      "mobileUrl": "https://api.toutiaoapi.com/feoffline/amos_land/new/html/main/index.html?topic_id=7625453500595621385"
    },
    {
      "id": "7625239644062023743",
      "title": "母亲不知儿子去世跟AI儿子聊了1年",
      "cover": "https://p26-sign.toutiaoimg.com/tos-cn-i-qvj2lq49k0/2bcef7dd378e497fad7e4b8db64e0aaf~tplv-tt-shrink:960:540.jpeg?_iz=30575&from=sign_default&lk3s=8d617dac&x-expires=1778025600&x-signature=CrJ2Jcs%2BEoVVMyqECzcCUEVtrTM%3D",
      "timestamp": 7625239644062024000,
      "hot": 17709484,
      "url": "https://www.toutiao.com/trending/7625239644062023743/",
      "mobileUrl": "https://api.toutiaoapi.com/feoffline/amos_land/new/html/main/index.html?topic_id=7625239644062023743"
    },
    {
      "id": "7625404033385332777",
      "title": "你如何看国米5-2大胜罗马",
      "cover": "https://p26-sign.toutiaoimg.com/tos-cn-i-qvj2lq49k0/468d270111ad4522a1004234b94e59c1~tplv-tt-shrink:960:540.jpeg?_iz=30575&from=sign_default&lk3s=8d617dac&x-expires=1778025600&x-signature=iP4PAsvFtBiJHmZYbL5Wg6DVLo0%3D",
      "timestamp": 7625404033385333000,
      "hot": 16024204,
      "url": "https://www.toutiao.com/trending/7625404033385332777/",
      "mobileUrl": "https://api.toutiaoapi.com/feoffline/amos_land/new/html/main/index.html?topic_id=7625404033385332777"
    },
    {
      "id": "7624898510541934134",
      "title": "伊朗公布击落12架美战机名单",
      "cover": "https://p3-sign.toutiaoimg.com/tos-cn-i-qvj2lq49k0/4ac19d7350dd4f9b928ccff088d9d75f~tplv-tt-shrink:960:540.jpeg?_iz=30575&from=sign_default&lk3s=8d617dac&x-expires=1778025600&x-signature=yNgi4V0FnCryN054HrxWbmdATco%3D",
      "timestamp": 7624898510541935000,
      "hot": 14499299,
      "url": "https://www.toutiao.com/trending/7624898510541934134/",
      "mobileUrl": "https://api.toutiaoapi.com/feoffline/amos_land/new/html/main/index.html?topic_id=7624898510541934134"
    },
    {
      "id": "7625312769474072107",
      "title": "孙颖莎与王曼昱颁奖典礼上热聊",
      "cover": "https://p3-sign.toutiaoimg.com/tos-cn-i-qvj2lq49k0/25aa373e999e4d44a96bbc5d94a84e77~tplv-tt-shrink:960:540.jpeg?_iz=30575&from=sign_default&lk3s=8d617dac&x-expires=1778025600&x-signature=G2kdovdMbqe0G67ZMrSEqFs2Bx4%3D",
      "timestamp": 7625312769474073000,
      "hot": 13119509,
      "url": "https://www.toutiao.com/trending/7625312769474072107/",
      "mobileUrl": "https://api.toutiaoapi.com/feoffline/amos_land/new/html/main/index.html?topic_id=7625312769474072107"
    },
    {
      "id": "7625428778054864422",
      "title": "周杰伦3小时演唱会实唱不足90分钟",
      "cover": "https://p26-sign.toutiaoimg.com/tos-cn-i-qvj2lq49k0/33889c20c5e7420b8f76072b96250b3a~tplv-tt-shrink:960:540.jpeg?_iz=30575&from=sign_default&lk3s=8d617dac&x-expires=1778025600&x-signature=0u%2BpRSbyX%2FLm2iNi0T9I0a5uoBQ%3D",
      "timestamp": 7625428778054865000,
      "hot": 11871022,
      "url": "https://www.toutiao.com/trending/7625428778054864422/",
      "mobileUrl": "https://api.toutiaoapi.com/feoffline/amos_land/new/html/main/index.html?topic_id=7625428778054864422"
    },
    {
      "id": "7625167359867125823",
      "title": "伊朗革命卫队：正备战波斯湾新秩序",
      "cover": "https://p26-sign.toutiaoimg.com/top-static-files-outer/breaknews/ef13b2cf-7301-481f-bdf9-adcc0bfd08ad~tplv-tt-shrink:960:540.jpeg?_iz=30575&from=sign_default&lk3s=8d617dac&x-expires=1778025600&x-signature=N%2FdVIJNd74OQ8T7L%2FtDRWmQkPP4%3D",
      "timestamp": 7625167359867126000,
      "hot": 10741345,
      "url": "https://www.toutiao.com/trending/7625167359867125823/",
      "mobileUrl": "https://api.toutiaoapi.com/feoffline/amos_land/new/html/main/index.html?topic_id=7625167359867125823"
    },
    {
      "id": "7624918669143506985",
      "title": "你被宠物的忠诚感动过吗",
      "cover": "https://p3-sign.toutiaoimg.com/tos-cn-i-qvj2lq49k0/6eb4450b70a14dc4be64b5457b34b56c~tplv-tt-shrink:960:540.jpeg?_iz=30575&from=sign_default&lk3s=8d617dac&x-expires=1778025600&x-signature=toetKkJwJDsDzU2ONFoeyMBGC3c%3D",
      "timestamp": 7624918669143507000,
      "hot": 9719171,
      "url": "https://www.toutiao.com/trending/7624918669143506985/",
      "mobileUrl": "https://api.toutiaoapi.com/feoffline/amos_land/new/html/main/index.html?topic_id=7624918669143506985"
    }
  ]
}