{
  "meta": {
    "platform": "toutiao",
    "date": "2026-03-13T02:05:27.937544",
    "count": 20
  },
  "data": [
    {
      "id": "7615901311695011882",
      "title": "一觉醒来 两箭发射成功",
      "cover": "https://p3-sign.toutiaoimg.com/tos-cn-i-qvj2lq49k0/7c1104ebe67949b68476e006b16527ea~tplv-tt-shrink:960:540.jpeg?_iz=30575&from=sign_default&lk3s=8d617dac&x-expires=1775952000&x-signature=xx0TpTe1coVkbJrjrAAjlK3mY%2BM%3D",
      "timestamp": 7615901311695012000,
      "hot": 27202403,
      "url": "https://www.toutiao.com/trending/7615901311695011882/",
      "mobileUrl": "https://api.toutiaoapi.com/feoffline/amos_land/new/html/main/index.html?topic_id=7615901311695011882"
    },
    {
      "id": "7616530270539370011",
      "title": "代表推进小班化教学建议被采纳",
      "cover": "https://p3-sign.toutiaoimg.com/tos-cn-i-qvj2lq49k0/1e38966bce4b42fc9bd1daae88cbaf2f~tplv-tt-shrink:960:540.jpeg?_iz=30575&from=sign_default&lk3s=8d617dac&x-expires=1775952000&x-signature=Batxe8MrybFpW3vK57Wfud8E%2FOs%3D",
      "timestamp": 7616530270539370000,
      "hot": 24613752,
      "url": "https://www.toutiao.com/trending/7616530270539370011/",
      "mobileUrl": "https://api.toutiaoapi.com/feoffline/amos_land/new/html/main/index.html?topic_id=7616530270539370011"
    },
    {
      "id": "7616141441898676243",
      "title": "为全球发展注入稳定性和正能量",
      "cover": "https://p3-sign.toutiaoimg.com/top-static-files-outer/breaknews/46ca29f6-dd29-4026-9400-8b3e46743e00~tplv-tt-shrink:960:540.jpeg?_iz=30575&from=sign_default&lk3s=8d617dac&x-expires=1775952000&x-signature=5j5dh8y75lIiO0HYB8f0YNwHXYA%3D",
      "timestamp": 7616141441898676000,
      "hot": 22271443,
      "url": "https://www.toutiao.com/trending/7616141441898676243/",
      "mobileUrl": "https://api.toutiaoapi.com/feoffline/amos_land/new/html/main/index.html?topic_id=7616141441898676243"
    },
    {
      "id": "7615841022916640819",
      "title": "“魔兽”霍华德宣布退役",
      "cover": "https://p26-sign.toutiaoimg.com/top-static-files-outer/breaknews/6e8f0643-f3af-469e-820e-ca07f54cd989~tplv-tt-shrink:960:540.jpeg?_iz=30575&from=sign_default&lk3s=8d617dac&x-expires=1775952000&x-signature=Z7waEwXN2Tk0zKbQ7rSpA15NBhk%3D",
      "timestamp": 7615841022916641000,
      "hot": 20152035,
      "url": "https://www.toutiao.com/trending/7615841022916640819/",
      "mobileUrl": "https://api.toutiaoapi.com/feoffline/amos_land/new/html/main/index.html?topic_id=7615841022916640819"
    },
    {
      "id": "7616211864494129206",
      "title": "苹果税下调",
      "cover": "https://p3-sign.toutiaoimg.com/top-static-files-outer/breaknews/67855e89-2d73-43c0-9ea8-071d95e815c2~tplv-tt-shrink:960:540.jpeg?_iz=30575&from=sign_default&lk3s=8d617dac&x-expires=1775952000&x-signature=DLxord1gsQZ34r6VDQPwqO8VOgs%3D",
      "timestamp": 7616211864494129000,
      "hot": 18234316,
      "url": "https://www.toutiao.com/trending/7616211864494129206/",
      "mobileUrl": "https://api.toutiaoapi.com/feoffline/amos_land/new/html/main/index.html?topic_id=7616211864494129206"
    },
    {
      "id": "7615541706667687946",
      "title": "伊朗称击落美加油机 机组人员均死亡",
      "cover": "https://p3-sign.toutiaoimg.com/tos-cn-i-qvj2lq49k0/1a69e3c18a164b92b50c88fe88d11634~tplv-tt-shrink:960:540.jpeg?_iz=30575&from=sign_default&lk3s=8d617dac&x-expires=1775952000&x-signature=%2FaNvqgMAETNSGZFhlKg%2BjTaXTu4%3D",
      "timestamp": 7615541706667688000,
      "hot": 16499091,
      "url": "https://www.toutiao.com/trending/7615541706667687946/",
      "mobileUrl": "https://api.toutiaoapi.com/feoffline/amos_land/new/html/main/index.html?topic_id=7615541706667687946"
    },
    {
      "id": "7615825414318309417",
      "title": "名嘴：日本若敢越雷池一步必粉身碎骨",
      "cover": "https://p3-sign.toutiaoimg.com/tos-cn-i-qvj2lq49k0/b5af1314423544679c23480f14b93b6c~tplv-tt-shrink:960:540.jpeg?_iz=30575&from=sign_default&lk3s=8d617dac&x-expires=1775952000&x-signature=%2FUpSRih2NUEGx%2Bt2BiHrmSPQ5mw%3D",
      "timestamp": 7615825414318309000,
      "hot": 14928995,
      "url": "https://www.toutiao.com/trending/7615825414318309417/",
      "mobileUrl": "https://api.toutiaoapi.com/feoffline/amos_land/new/html/main/index.html?topic_id=7615825414318309417"
    },
    {
      "id": "7616297232433761835",
      "title": "司法部将在全国统一推行扫码入企",
      "cover": "https://p3-sign.toutiaoimg.com/top-static-files-outer/breaknews/793dc937-f3b7-4b97-9647-89bb9105b415~tplv-tt-shrink:960:540.jpeg?_iz=30575&from=sign_default&lk3s=8d617dac&x-expires=1775952000&x-signature=Y%2BcFQrmWI6xKtUZurB6IyDwFNfI%3D",
      "timestamp": 7616297232433762000,
      "hot": 13508313,
      "url": "https://www.toutiao.com/trending/7616297232433761835/",
      "mobileUrl": "https://api.toutiaoapi.com/feoffline/amos_land/new/html/main/index.html?topic_id=7616297232433761835"
    },
    {
      "id": "7616376944103509550",
      "title": "两会现场速递",
      "cover": "https://p3-sign.toutiaoimg.com/tos-cn-i-qvj2lq49k0/34eb430854ed4e24b95c5917426dbd15~tplv-tt-shrink:960:540.jpeg?_iz=30575&from=sign_default&lk3s=8d617dac&x-expires=1775952000&x-signature=F7wjpsbGB3iteD9ClNAZ%2BPAyI%2Fc%3D",
      "timestamp": 7616376944103510000,
      "hot": 12222827,
      "url": "https://www.toutiao.com/trending/7616376944103509550/",
      "mobileUrl": "https://api.toutiaoapi.com/feoffline/amos_land/new/html/main/index.html?topic_id=7616376944103509550"
    },
    {
      "id": "7615267437721780267",
      "title": "中方回应特朗普计划访华",
      "cover": "https://p3-sign.toutiaoimg.com/top-static-files-outer/breaknews/9480d289-4950-46b6-9b2a-9cefd2cd6942~tplv-tt-shrink:960:540.jpeg?_iz=30575&from=sign_default&lk3s=8d617dac&x-expires=1775952000&x-signature=VczKks8CEZz%2BwR0gaohiWKCu5ok%3D",
      "timestamp": 7615267437721780000,
      "hot": 11059671,
      "url": "https://www.toutiao.com/trending/7615267437721780267/",
      "mobileUrl": "https://api.toutiaoapi.com/feoffline/amos_land/new/html/main/index.html?topic_id=7615267437721780267"
    },
    {
      "id": "7615958298823049243",
      "title": "异地救护车太原拐卖儿童？假的",
      "cover": "https://p26-sign.toutiaoimg.com/top-static-files-outer/breaknews/74ab1ff3-f55d-4dd9-a2fb-c4b63fb6c1f0~tplv-tt-shrink:960:540.jpeg?_iz=30575&from=sign_default&lk3s=8d617dac&x-expires=1775952000&x-signature=5YX0qDa0yHKrD24KT%2FrgfmpQB%2Bk%3D",
      "timestamp": 7615958298823049000,
      "hot": 10007204,
      "url": "https://www.toutiao.com/trending/7615958298823049243/",
      "mobileUrl": "https://api.toutiaoapi.com/feoffline/amos_land/new/html/main/index.html?topic_id=7615958298823049243"
    },
    {
      "id": "7616538009198054950",
      "title": "特朗普：穆杰塔巴可能受伤但活着",
      "cover": "https://p3-sign.toutiaoimg.com/tos-cn-i-qvj2lq49k0/5c4095d37faf4411af4006c26361e742~tplv-tt-shrink:960:540.jpeg?_iz=30575&from=sign_default&lk3s=8d617dac&x-expires=1775952000&x-signature=2vtAVXfIjpqUoxx0ibQMzbdai3U%3D",
      "timestamp": 7616538009198055000,
      "hot": 9054893,
      "url": "https://www.toutiao.com/trending/7616538009198054950/",
      "mobileUrl": "https://api.toutiaoapi.com/feoffline/amos_land/new/html/main/index.html?topic_id=7616538009198054950"
    },
    {
      "id": "7615941078433464374",
      "title": "伊朗最高领袖发布个人照片",
      "cover": "https://p3-sign.toutiaoimg.com/tos-cn-i-qvj2lq49k0/34744f420ce94657bd3b430e8570a4c2~tplv-tt-shrink:960:540.jpeg?_iz=30575&from=sign_default&lk3s=8d617dac&x-expires=1775952000&x-signature=%2BZBTUb0sunysG05PgNRRVLxY7Mk%3D",
      "timestamp": 7615941078433464000,
      "hot": 8193206,
      "url": "https://www.toutiao.com/trending/7615941078433464374/",
      "mobileUrl": "https://api.toutiaoapi.com/feoffline/amos_land/new/html/main/index.html?topic_id=7615941078433464374"
    },
    {
      "id": "7616303643654815782",
      "title": "妈妈用平底锅烫出“无孔拼豆”",
      "cover": "https://p3-sign.toutiaoimg.com/top-static-files-outer/breaknews/d7b6a288-91c0-4431-bf30-119ca85c2951~tplv-tt-shrink:960:540.jpeg?_iz=30575&from=sign_default&lk3s=8d617dac&x-expires=1775952000&x-signature=326vE88CuhEiwmQE14H0qIX7Uws%3D",
      "timestamp": 7616303643654816000,
      "hot": 7413519,
      "url": "https://www.toutiao.com/trending/7616303643654815782/",
      "mobileUrl": "https://api.toutiaoapi.com/feoffline/amos_land/new/html/main/index.html?topic_id=7616303643654815782"
    },
    {
      "id": "7615837960902053395",
      "title": "农民养老金提高至1000元分几步走",
      "cover": "https://p3-sign.toutiaoimg.com/tos-cn-i-qvj2lq49k0/66fdc926d5024856aa995e0201dcb444~tplv-tt-shrink:960:540.jpeg?_iz=30575&from=sign_default&lk3s=8d617dac&x-expires=1775952000&x-signature=pKWjfjVGI5c2bqwOBvrvhOENYGM%3D",
      "timestamp": 7615837960902054000,
      "hot": 6708030,
      "url": "https://www.toutiao.com/trending/7615837960902053395/",
      "mobileUrl": "https://api.toutiaoapi.com/feoffline/amos_land/new/html/main/index.html?topic_id=7615837960902053395"
    },
    {
      "id": "7615805340906733614",
      "title": "伊朗公布美基地遭袭前后卫星图像",
      "cover": "https://p3-sign.toutiaoimg.com/tos-cn-i-qvj2lq49k0/cb3f3087e2794a73bbdc7ddd0c1dc3a3~tplv-tt-shrink:960:540.jpeg?_iz=30575&from=sign_default&lk3s=8d617dac&x-expires=1775952000&x-signature=60JxxEPmSl9UfMC%2Feg3AygJiLQY%3D",
      "timestamp": 7615805340906734000,
      "hot": 6069676,
      "url": "https://www.toutiao.com/trending/7615805340906733614/",
      "mobileUrl": "https://api.toutiaoapi.com/feoffline/amos_land/new/html/main/index.html?topic_id=7615805340906733614"
    },
    {
      "id": "7615511177006710790",
      "title": "男子做核磁被忘机器上一夜 医生停职",
      "cover": "https://p3-sign.toutiaoimg.com/tos-cn-i-qvj2lq49k0/7891e41e97164e339f8aa2faf3e53252~tplv-tt-shrink:960:540.jpeg?_iz=30575&from=sign_default&lk3s=8d617dac&x-expires=1775952000&x-signature=9p0mROyxrmOExVsDTn%2B146MfVAI%3D",
      "timestamp": 7615511177006711000,
      "hot": 5492070,
      "url": "https://www.toutiao.com/trending/7615511177006710790/",
      "mobileUrl": "https://api.toutiaoapi.com/feoffline/amos_land/new/html/main/index.html?topic_id=7615511177006710790"
    },
    {
      "id": "7616344663603707923",
      "title": "人大代表示范“米字操”",
      "cover": "https://p26-sign.toutiaoimg.com/tos-cn-i-qvj2lq49k0/dd30682583354e6d83e80f444812b679~tplv-tt-shrink:960:540.jpeg?_iz=30575&from=sign_default&lk3s=8d617dac&x-expires=1775952000&x-signature=ek7agEc2fDqtwa0AHuqKCsZJLGM%3D",
      "timestamp": 7616344663603708000,
      "hot": 4969430,
      "url": "https://www.toutiao.com/trending/7616344663603707923/",
      "mobileUrl": "https://api.toutiaoapi.com/feoffline/amos_land/new/html/main/index.html?topic_id=7616344663603707923"
    },
    {
      "id": "7616297232433860139",
      "title": "伊朗称部分国家船只可过霍尔木兹海峡",
      "cover": "https://p3-sign.toutiaoimg.com/tos-cn-i-qvj2lq49k0/c1acce7463014c4a9af880869428c5a4~tplv-tt-shrink:960:540.jpeg?_iz=30575&from=sign_default&lk3s=8d617dac&x-expires=1775952000&x-signature=LN1nRmmIlHjpkyMAa9Q%2FfTWqDJ0%3D",
      "timestamp": 7616297232433861000,
      "hot": 4496526,
      "url": "https://www.toutiao.com/trending/7616297232433860139/",
      "mobileUrl": "https://api.toutiaoapi.com/feoffline/amos_land/new/html/main/index.html?topic_id=7616297232433860139"
    },
    {
      "id": "7615804925905420329",
      "title": "卡里突然多了1万5 转账人坚称没转错",
      "cover": "https://p3-sign.toutiaoimg.com/tos-cn-i-qvj2lq49k0/bda5c859abfd41c3826296fbba17a47c~tplv-tt-shrink:960:540.jpeg?_iz=30575&from=sign_default&lk3s=8d617dac&x-expires=1775952000&x-signature=dsJIazOkV3duLS%2FTpN8dG%2FVmNkg%3D",
      "timestamp": 7615804925905420000,
      "hot": 4068625,
      "url": "https://www.toutiao.com/trending/7615804925905420329/",
      "mobileUrl": "https://api.toutiaoapi.com/feoffline/amos_land/new/html/main/index.html?topic_id=7615804925905420329"
    }
  ]
}