{
  "meta": {
    "platform": "douyin",
    "date": "2026-02-04T02:04:14.814539",
    "count": 20
  },
  "data": [
    {
      "id": "2388818",
      "title": "今日立春",
      "timestamp": 1770160384000,
      "hot": 12132470,
      "url": "https://www.douyin.com/hot/2388818",
      "mobileUrl": "https://www.douyin.com/hot/2388818"
    },
    {
      "id": "2388095",
      "title": "记录我的春运返乡故事",
      "timestamp": 1770091989000,
      "hot": 11515315,
      "url": "https://www.douyin.com/hot/2388095",
      "mobileUrl": "https://www.douyin.com/hot/2388095"
    },
    {
      "id": "2388571",
      "title": "2026中央一号文件发布",
      "timestamp": 1770113928000,
      "hot": 11336536,
      "url": "https://www.douyin.com/hot/2388571",
      "mobileUrl": "https://www.douyin.com/hot/2388571"
    },
    {
      "id": "2388769",
      "title": "半个娱乐圈都在平板支撑挑战",
      "timestamp": 1770127829000,
      "hot": 10885872,
      "url": "https://www.douyin.com/hot/2388769",
      "mobileUrl": "https://www.douyin.com/hot/2388769"
    },
    {
      "id": "2387866",
      "title": "走过属于我们的冬天",
      "timestamp": 1770080812000,
      "hot": 10271935,
      "url": "https://www.douyin.com/hot/2387866",
      "mobileUrl": "https://www.douyin.com/hot/2387866"
    },
    {
      "id": "2388414",
      "title": "万物皆可拼豆",
      "timestamp": 1770106285000,
      "hot": 10197666,
      "url": "https://www.douyin.com/hot/2388414",
      "mobileUrl": "https://www.douyin.com/hot/2388414"
    },
    {
      "id": "2388899",
      "title": "哈登被快船交易至骑士",
      "timestamp": 1770167547000,
      "hot": 9061448,
      "url": "https://www.douyin.com/hot/2388899",
      "mobileUrl": "https://www.douyin.com/hot/2388899"
    },
    {
      "id": "2388820",
      "title": "美军击落伊朗无人机",
      "timestamp": 1770161090000,
      "hot": 8992518,
      "url": "https://www.douyin.com/hot/2388820",
      "mobileUrl": "https://www.douyin.com/hot/2388820"
    },
    {
      "id": "2388791",
      "title": "在线等一个共创机会",
      "timestamp": 1770130036000,
      "hot": 8754207,
      "url": "https://www.douyin.com/hot/2388791",
      "mobileUrl": "https://www.douyin.com/hot/2388791"
    },
    {
      "id": "2388894",
      "title": "现货黄金重新站上5000美元",
      "timestamp": 1770167137000,
      "hot": 8488905,
      "url": "https://www.douyin.com/hot/2388894",
      "mobileUrl": "https://www.douyin.com/hot/2388894"
    },
    {
      "id": "2388478",
      "title": "俄方向日本发出警告",
      "timestamp": 1770109711000,
      "hot": 8272889,
      "url": "https://www.douyin.com/hot/2388478",
      "mobileUrl": "https://www.douyin.com/hot/2388478"
    },
    {
      "id": "2388626",
      "title": "多地网传“人贩子出没”系谣言",
      "timestamp": 1770117661000,
      "hot": 8218762,
      "url": "https://www.douyin.com/hot/2388626",
      "mobileUrl": "https://www.douyin.com/hot/2388626"
    },
    {
      "id": "2388648",
      "title": "立春吃出仪式感",
      "timestamp": 1770118838000,
      "hot": 8155827,
      "url": "https://www.douyin.com/hot/2388648",
      "mobileUrl": "https://www.douyin.com/hot/2388648"
    },
    {
      "id": "2388221",
      "title": "风过留痕凶手可怜又可恨",
      "timestamp": 1770099587000,
      "hot": 8050705,
      "url": "https://www.douyin.com/hot/2388221",
      "mobileUrl": "https://www.douyin.com/hot/2388221"
    },
    {
      "id": "2388122",
      "title": "被冬奥会中国代表团队服种草了",
      "timestamp": 1770094661000,
      "hot": 7786226,
      "url": "https://www.douyin.com/hot/2388122",
      "mobileUrl": "https://www.douyin.com/hot/2388122"
    },
    {
      "id": "2388789",
      "title": "警方通报“夫妻吃娃娃菜中毒”",
      "timestamp": 1770129821000,
      "hot": 7758420,
      "url": "https://www.douyin.com/hot/2388789",
      "mobileUrl": "https://www.douyin.com/hot/2388789"
    },
    {
      "id": "2387650",
      "title": "嘉禾望岗为什么火了",
      "timestamp": 1770038221000,
      "hot": 7739828,
      "url": "https://www.douyin.com/hot/2387650",
      "mobileUrl": "https://www.douyin.com/hot/2387650"
    },
    {
      "id": "2388141",
      "title": "爱泼斯坦案“吃人”传闻是真的吗",
      "timestamp": 1770095302000,
      "hot": 7738599,
      "url": "https://www.douyin.com/hot/2388141",
      "mobileUrl": "https://www.douyin.com/hot/2388141"
    },
    {
      "id": "2388070",
      "title": "生命树三百元买下传家宝",
      "timestamp": 1770089826000,
      "hot": 7734121,
      "url": "https://www.douyin.com/hot/2388070",
      "mobileUrl": "https://www.douyin.com/hot/2388070"
    },
    {
      "id": "2388159",
      "title": "春节美食挑战赛轮番开场啦",
      "timestamp": 1770095672000,
      "hot": 7732331,
      "url": "https://www.douyin.com/hot/2388159",
      "mobileUrl": "https://www.douyin.com/hot/2388159"
    }
  ]
}