{
  "meta": {
    "platform": "toutiao",
    "date": "2026-03-31T02:27:14.285400",
    "count": 20
  },
  "data": [
    {
      "id": "7621978651006353427",
      "title": "韩国向中国14个城市发放十年签",
      "cover": "https://p3-sign.toutiaoimg.com/tos-cn-i-qvj2lq49k0/5e297d18f9d24b6286b4bd2b70b8acdc~tplv-tt-shrink:960:540.jpeg?_iz=30575&from=sign_default&lk3s=8d617dac&x-expires=1777507200&x-signature=8pgiFufz8IktNnMg91%2BnZDIXEaE%3D",
      "timestamp": 7621978651006353000,
      "hot": 57111932,
      "url": "https://www.toutiao.com/trending/7621978651006353427/",
      "mobileUrl": "https://api.toutiaoapi.com/feoffline/amos_land/new/html/main/index.html?topic_id=7621978651006353427"
    },
    {
      "id": "7623191296034754084",
      "title": "郑丽文访陆随行人员名单公布",
      "cover": "https://p3-sign.toutiaoimg.com/top-static-files-outer/breaknews/ceb0ab1d-4393-4203-be64-292e3794019c~tplv-tt-shrink:960:540.jpeg?_iz=30575&from=sign_default&lk3s=8d617dac&x-expires=1777507200&x-signature=yLurdX4vDuSAHkg9picSufG0pss%3D",
      "timestamp": 7623191296034755000,
      "hot": 51677013,
      "url": "https://www.toutiao.com/trending/7623191296034754084/",
      "mobileUrl": "https://api.toutiaoapi.com/feoffline/amos_land/new/html/main/index.html?topic_id=7623191296034754084"
    },
    {
      "id": "7622863629935558675",
      "title": "具身智能领域首份行业标准发布",
      "cover": "https://p3-sign.toutiaoimg.com/tos-cn-i-qvj2lq49k0/69ca46663ca0490eab46a4e6a6f7cba6~tplv-tt-shrink:960:540.jpeg?_iz=30575&from=sign_default&lk3s=8d617dac&x-expires=1777507200&x-signature=l7xdu8%2F5kxgI7R%2BDRMhdvsVx6Do%3D",
      "timestamp": 7622863629935559000,
      "hot": 46759295,
      "url": "https://www.toutiao.com/trending/7622863629935558675/",
      "mobileUrl": "https://api.toutiaoapi.com/feoffline/amos_land/new/html/main/index.html?topic_id=7622863629935558675"
    },
    {
      "id": "7622963824888545343",
      "title": "张雪称将吃掉国际大牌超50%份额",
      "cover": "https://p3-sign.toutiaoimg.com/tos-cn-i-qvj2lq49k0/d29c5757439a4b6ba8b10dd614a2cbbc~tplv-tt-shrink:960:540.jpeg?_iz=30575&from=sign_default&lk3s=8d617dac&x-expires=1777507200&x-signature=IfvswRNFFUqwWiwqMKeOqwO9OMo%3D",
      "timestamp": 7622963824888545000,
      "hot": 42309559,
      "url": "https://www.toutiao.com/trending/7622963824888545343/",
      "mobileUrl": "https://api.toutiaoapi.com/feoffline/amos_land/new/html/main/index.html?topic_id=7622963824888545343"
    },
    {
      "id": "7623211957360791086",
      "title": "重庆一隧道发生爆炸事故致4死9伤",
      "cover": "https://p3-sign.toutiaoimg.com/top-static-files-outer/breaknews/582f7aae-b7b6-4c10-96e8-ee71c4ae01ac~tplv-tt-shrink:960:540.jpeg?_iz=30575&from=sign_default&lk3s=8d617dac&x-expires=1777507200&x-signature=ilIHWp6dCI9S%2F%2BaYSR2vzV0zlak%3D",
      "timestamp": 7623211957360792000,
      "hot": 38283272,
      "url": "https://www.toutiao.com/trending/7623211957360791086/",
      "mobileUrl": "https://api.toutiaoapi.com/feoffline/amos_land/new/html/main/index.html?topic_id=7623211957360791086"
    },
    {
      "id": "7622952841149628425",
      "title": "美客机从巴西起飞后发动机爆炸",
      "cover": "https://p3-sign.toutiaoimg.com/tos-cn-i-qvj2lq49k0/b8cde2454d8449efa54f4b81125b1346~tplv-tt-shrink:960:540.jpeg?_iz=30575&from=sign_default&lk3s=8d617dac&x-expires=1777507200&x-signature=AC5D3fL6vaUKXcODv7SrC2YlPBs%3D",
      "timestamp": 7622952841149628000,
      "hot": 34640137,
      "url": "https://www.toutiao.com/trending/7622952841149628425/",
      "mobileUrl": "https://api.toutiaoapi.com/feoffline/amos_land/new/html/main/index.html?topic_id=7622952841149628425"
    },
    {
      "id": "7622737197472464959",
      "title": "预计2035年中国不孕不育夫妇7440万对",
      "cover": "https://p3-sign.toutiaoimg.com/tos-cn-i-qvj2lq49k0/8ac429e4ca3c41c09d3ec972bce05023~tplv-tt-shrink:960:540.jpeg?_iz=30575&from=sign_default&lk3s=8d617dac&x-expires=1777507200&x-signature=WV9AWDdd7IBUDv7i8DL9A3BrJLM%3D",
      "timestamp": 7622737197472465000,
      "hot": 31343692,
      "url": "https://www.toutiao.com/trending/7622737197472464959/",
      "mobileUrl": "https://api.toutiaoapi.com/feoffline/amos_land/new/html/main/index.html?topic_id=7622737197472464959"
    },
    {
      "id": "7623198352552758793",
      "title": "媒体人：张雪让中国摩托站上世界之巅",
      "cover": "https://p3-sign.toutiaoimg.com/top-static-files-outer/breaknews/a6217186-743a-4386-8f6b-00234311554d~tplv-tt-shrink:960:540.jpeg?_iz=30575&from=sign_default&lk3s=8d617dac&x-expires=1777507200&x-signature=6UtlDg0IDU3%2FD1hIrXD6QnqsmLM%3D",
      "timestamp": 7623198352552759000,
      "hot": 28360946,
      "url": "https://www.toutiao.com/trending/7623198352552758793/",
      "mobileUrl": "https://api.toutiaoapi.com/feoffline/amos_land/new/html/main/index.html?topic_id=7623198352552758793"
    },
    {
      "id": "7622902714294075446",
      "title": "光大银行2025年归母净利润388.26亿",
      "cover": "https://p3-sign.toutiaoimg.com/top-static-files-outer/breaknews/1446b91d-bece-4f9e-b873-36bb277bc731~tplv-tt-shrink:960:540.jpeg?_iz=30575&from=sign_default&lk3s=8d617dac&x-expires=1777507200&x-signature=H%2BnOqG9aDp3j%2BMBGG%2FcWaSV46fc%3D",
      "timestamp": 7622902714294075000,
      "hot": 25662045,
      "url": "https://www.toutiao.com/trending/7622902714294075446/",
      "mobileUrl": "https://api.toutiaoapi.com/feoffline/amos_land/new/html/main/index.html?topic_id=7622902714294075446"
    },
    {
      "id": "7623205458349834250",
      "title": "28岁在意失联川大博士遗体已找到",
      "cover": "https://p3-sign.toutiaoimg.com/tos-cn-i-qvj2lq49k0/129e930a4c75478e96c06d6ce66efcb1~tplv-tt-shrink:960:540.jpeg?_iz=30575&from=sign_default&lk3s=8d617dac&x-expires=1777507200&x-signature=OX%2FW0dImVuURPtoSb8gnuNj5LdU%3D",
      "timestamp": 7623205458349834000,
      "hot": 23219978,
      "url": "https://www.toutiao.com/trending/7623205458349834250/",
      "mobileUrl": "https://api.toutiaoapi.com/feoffline/amos_land/new/html/main/index.html?topic_id=7623205458349834250"
    },
    {
      "id": "7622163802884423743",
      "title": "高三男孩在喀纳斯湖失踪系谣言",
      "cover": "https://p9-sign.toutiaoimg.com/tos-cn-i-qvj2lq49k0/6f6257a310be48de82d66954666aaa84~tplv-tt-shrink:960:540.jpeg?_iz=30575&from=sign_default&lk3s=8d617dac&x-expires=1777507200&x-signature=i7xNT2wfEk1d13gt9reFYj3J6%2Bo%3D",
      "timestamp": 7622163802884424000,
      "hot": 21010305,
      "url": "https://www.toutiao.com/trending/7622163802884423743/",
      "mobileUrl": "https://api.toutiaoapi.com/feoffline/amos_land/new/html/main/index.html?topic_id=7622163802884423743"
    },
    {
      "id": "7623217627933969961",
      "title": "特朗普愿在霍尔木兹关闭状态下停战",
      "cover": "https://p3-sign.toutiaoimg.com/top-static-files-outer/breaknews/8cb9587c-f1c4-4839-8758-136ebcb9723d~tplv-tt-shrink:960:540.jpeg?_iz=30575&from=sign_default&lk3s=8d617dac&x-expires=1777507200&x-signature=ZHZpAEQlha8dYGEVe9hKsR%2F2H78%3D",
      "timestamp": 7623217627933970000,
      "hot": 19010910,
      "url": "https://www.toutiao.com/trending/7623217627933969961/",
      "mobileUrl": "https://api.toutiaoapi.com/feoffline/amos_land/new/html/main/index.html?topic_id=7623217627933969961"
    },
    {
      "id": "7623092777148334122",
      "title": "香港演员施明去世",
      "cover": "https://p3-sign.toutiaoimg.com/tos-cn-i-qvj2lq49k0/6535939dc1c143289a7d922c3136ed02~tplv-tt-shrink:960:540.jpeg?_iz=30575&from=sign_default&lk3s=8d617dac&x-expires=1777507200&x-signature=L7j69ScFmODiK1U2k1LN6IpsosM%3D",
      "timestamp": 7623092777148334000,
      "hot": 17201783,
      "url": "https://www.toutiao.com/trending/7623092777148334122/",
      "mobileUrl": "https://api.toutiaoapi.com/feoffline/amos_land/new/html/main/index.html?topic_id=7623092777148334122"
    },
    {
      "id": "7622636371529990150",
      "title": "孙颖莎回应成功卫冕将创造历史",
      "cover": "https://p3-sign.toutiaoimg.com/tos-cn-i-qvj2lq49k0/d380e6afe438425f932d68da63900f1e~tplv-tt-shrink:960:540.jpeg?_iz=30575&from=sign_default&lk3s=8d617dac&x-expires=1777507200&x-signature=1PzWaTM7zui6ieIPCcmVF7pJSgI%3D",
      "timestamp": 7622636371529990000,
      "hot": 15564817,
      "url": "https://www.toutiao.com/trending/7622636371529990150/",
      "mobileUrl": "https://api.toutiaoapi.com/feoffline/amos_land/new/html/main/index.html?topic_id=7622636371529990150"
    },
    {
      "id": "7622140607867224091",
      "title": "车主28万盲订小鹏 半年进5次4S店",
      "cover": "https://p3-sign.toutiaoimg.com/tos-cn-i-qvj2lq49k0/33488037b8f1428996a9d261d22895a9~tplv-tt-shrink:960:540.jpeg?_iz=30575&from=sign_default&lk3s=8d617dac&x-expires=1777507200&x-signature=T6e7bBoDHaz9zU6RFuj2PELa9ds%3D",
      "timestamp": 7622140607867224000,
      "hot": 14083629,
      "url": "https://www.toutiao.com/trending/7622140607867224091/",
      "mobileUrl": "https://api.toutiaoapi.com/feoffline/amos_land/new/html/main/index.html?topic_id=7622140607867224091"
    },
    {
      "id": "7623046330512588806",
      "title": "100元体验1小时挖笋 名额1分钟抢光",
      "cover": "https://p3-sign.toutiaoimg.com/tos-cn-i-qvj2lq49k0/4d215597ef4347e7805e087ed5563567~tplv-tt-shrink:960:540.jpeg?_iz=30575&from=sign_default&lk3s=8d617dac&x-expires=1777507200&x-signature=F6cbeoQTXDhWR3CcmMsp%2Bk8YCZE%3D",
      "timestamp": 7623046330512589000,
      "hot": 12743394,
      "url": "https://www.toutiao.com/trending/7623046330512588806/",
      "mobileUrl": "https://api.toutiaoapi.com/feoffline/amos_land/new/html/main/index.html?topic_id=7623046330512588806"
    },
    {
      "id": "7622603024216932388",
      "title": "哈佛教授：人民币将在5年内成储备货币",
      "cover": "https://p3-sign.toutiaoimg.com/tos-cn-i-qvj2lq49k0/8d07ed3a578946d483867fe601b79cc6~tplv-tt-shrink:960:540.jpeg?_iz=30575&from=sign_default&lk3s=8d617dac&x-expires=1777507200&x-signature=%2BWV0%2Fqy0tkyIjrm9ROE%2F%2B%2FQbdqo%3D",
      "timestamp": 7622603024216932000,
      "hot": 11530700,
      "url": "https://www.toutiao.com/trending/7622603024216932388/",
      "mobileUrl": "https://api.toutiaoapi.com/feoffline/amos_land/new/html/main/index.html?topic_id=7622603024216932388"
    },
    {
      "id": "7622936054081749046",
      "title": "WCBA卫冕冠军东莞队被横扫你咋看",
      "cover": "https://p3-sign.toutiaoimg.com/tos-cn-i-qvj2lq49k0/38c4a6c8cb5a4cd88f1e5af9e1d2a833~tplv-tt-shrink:960:540.jpeg?_iz=30575&from=sign_default&lk3s=8d617dac&x-expires=1777507200&x-signature=iXXw9kQ357OcslCM8hxnTUsysOE%3D",
      "timestamp": 7622936054081749000,
      "hot": 10433409,
      "url": "https://www.toutiao.com/trending/7622936054081749046/",
      "mobileUrl": "https://api.toutiaoapi.com/feoffline/amos_land/new/html/main/index.html?topic_id=7622936054081749046"
    },
    {
      "id": "7621916081815552050",
      "title": "初中生放学路上即兴起舞",
      "cover": "https://p3-sign.toutiaoimg.com/tos-cn-i-qvj2lq49k0/ce7b279561b34fd286e322eacd2b6836~tplv-tt-shrink:960:540.jpeg?_iz=30575&from=sign_default&lk3s=8d617dac&x-expires=1777507200&x-signature=VV%2BGj44pwAfw1byA3qdUl22n6uE%3D",
      "timestamp": 7621916081815552000,
      "hot": 9440538,
      "url": "https://www.toutiao.com/trending/7621916081815552050/",
      "mobileUrl": "https://api.toutiaoapi.com/feoffline/amos_land/new/html/main/index.html?topic_id=7621916081815552050"
    },
    {
      "id": "7622699994264616979",
      "title": "那英唱三五句也要问版权问题",
      "cover": "https://p3-sign.toutiaoimg.com/tos-cn-i-qvj2lq49k0/8a2ddafae4624fa6b118b39aaada1476~tplv-tt-shrink:960:540.jpeg?_iz=30575&from=sign_default&lk3s=8d617dac&x-expires=1777507200&x-signature=PY0blCOggMp99MhRLlI2kufrJdo%3D",
      "timestamp": 7622699994264617000,
      "hot": 8542152,
      "url": "https://www.toutiao.com/trending/7622699994264616979/",
      "mobileUrl": "https://api.toutiaoapi.com/feoffline/amos_land/new/html/main/index.html?topic_id=7622699994264616979"
    }
  ]
}