{
  "meta": {
    "platform": "zhihu-daily",
    "date": "2025-05-30T01:27:07.042457",
    "count": 4
  },
  "data": [
    {
      "id": 9781477,
      "title": "人类为什么就不像动物，只需要在父母身边学习几个月就能独立生存？",
      "cover": "https://pic1.zhimg.com/v2-06b9270c17d05a4fb94d44b7cf810b1d.jpg?source=8673f162",
      "author": "瞻云 · 9 分钟阅读",
      "url": "https://daily.zhihu.com/story/9781477",
      "mobileUrl": "https://daily.zhihu.com/story/9781477"
    },
    {
      "id": 9781467,
      "title": "神经细胞最长能超一米，若中间发生断肢，缝合后该细胞怎么恢复原长度？",
      "cover": "https://picx.zhimg.com/v2-8a2e34235eaed11b6c9319cb0a33df55.jpg?source=8673f162",
      "author": "知乎用户 · 2 分钟阅读",
      "url": "https://daily.zhihu.com/story/9781467",
      "mobileUrl": "https://daily.zhihu.com/story/9781467"
    },
    {
      "id": 9781469,
      "title": "为什么信息不是能量？",
      "cover": "https://picx.zhimg.com/v2-fef2b51a715384a39b508fc95e3a7e06.jpg?source=8673f162",
      "author": "张英锋 · 18 分钟阅读",
      "url": "https://daily.zhihu.com/story/9781469",
      "mobileUrl": "https://daily.zhihu.com/story/9781469"
    },
    {
      "id": 9781484,
      "title": "瞎扯 · 如何正确地吐槽",
      "cover": "https://picx.zhimg.com/v2-6f7fc115fc9b281e845a89a66ee960f6.jpg?source=8673f162",
      "author": "VOL.3666",
      "url": "https://daily.zhihu.com/story/9781484",
      "mobileUrl": "https://daily.zhihu.com/story/9781484"
    }
  ]
}