{
  "meta": {
    "platform": "sina",
    "date": "2025-07-21T01:51:49.940909",
    "count": 20
  },
  "data": [
    {
      "id": "17ae34b90391b15c574244a89ca4c23d",
      "title": "央视曝光领导视察才开门的农村公厕",
      "hot": 4420000,
      "url": "https://so.sina.cn/search/list.d.html?keyword=%E5%A4%AE%E8%A7%86%E6%9B%9D%E5%85%89%E9%A2%86%E5%AF%BC%E8%A7%86%E5%AF%9F%E6%89%8D%E5%BC%80%E9%97%A8%E7%9A%84%E5%86%9C%E6%9D%91%E5%85%AC%E5%8E%95",
      "mobileUrl": "https://so.sina.cn/search/list.d.html?keyword=%E5%A4%AE%E8%A7%86%E6%9B%9D%E5%85%89%E9%A2%86%E5%AF%BC%E8%A7%86%E5%AF%9F%E6%89%8D%E5%BC%80%E9%97%A8%E7%9A%84%E5%86%9C%E6%9D%91%E5%85%AC%E5%8E%95"
    },
    {
      "id": "0bab4e8e5a26c0f0f4d2a03fd5c73ea6",
      "title": "400斤石头漂浮恒河被膜拜",
      "hot": 4210000,
      "url": "https://so.sina.cn/search/list.d.html?keyword=400%E6%96%A4%E7%9F%B3%E5%A4%B4%E6%BC%82%E6%B5%AE%E6%81%92%E6%B2%B3%E8%A2%AB%E8%86%9C%E6%8B%9C",
      "mobileUrl": "https://so.sina.cn/search/list.d.html?keyword=400%E6%96%A4%E7%9F%B3%E5%A4%B4%E6%BC%82%E6%B5%AE%E6%81%92%E6%B2%B3%E8%A2%AB%E8%86%9C%E6%8B%9C"
    },
    {
      "id": "e9e949fd9ad5d621216dbc726c3dd84c",
      "title": "老人肯德基店内占座乘凉",
      "hot": 3720000,
      "url": "https://so.sina.cn/search/list.d.html?keyword=%E8%80%81%E4%BA%BA%E8%82%AF%E5%BE%B7%E5%9F%BA%E5%BA%97%E5%86%85%E5%8D%A0%E5%BA%A7%E4%B9%98%E5%87%89",
      "mobileUrl": "https://so.sina.cn/search/list.d.html?keyword=%E8%80%81%E4%BA%BA%E8%82%AF%E5%BE%B7%E5%9F%BA%E5%BA%97%E5%86%85%E5%8D%A0%E5%BA%A7%E4%B9%98%E5%87%89"
    },
    {
      "id": "12bd1a082a6e5900a22fb5fd810b3a66",
      "title": "韩女子咬断性侵者舌头被判刑",
      "hot": 3530000,
      "url": "https://so.sina.cn/search/list.d.html?keyword=%E9%9F%A9%E5%A5%B3%E5%AD%90%E5%92%AC%E6%96%AD%E6%80%A7%E4%BE%B5%E8%80%85%E8%88%8C%E5%A4%B4%E8%A2%AB%E5%88%A4%E5%88%91",
      "mobileUrl": "https://so.sina.cn/search/list.d.html?keyword=%E9%9F%A9%E5%A5%B3%E5%AD%90%E5%92%AC%E6%96%AD%E6%80%A7%E4%BE%B5%E8%80%85%E8%88%8C%E5%A4%B4%E8%A2%AB%E5%88%A4%E5%88%91"
    },
    {
      "id": "74ece22378f46478ea41ee8cf8ab92d2",
      "title": "女生为交社保被负债200万",
      "hot": 3340000,
      "url": "https://so.sina.cn/search/list.d.html?keyword=%E5%A5%B3%E7%94%9F%E4%B8%BA%E4%BA%A4%E7%A4%BE%E4%BF%9D%E8%A2%AB%E8%B4%9F%E5%80%BA200%E4%B8%87",
      "mobileUrl": "https://so.sina.cn/search/list.d.html?keyword=%E5%A5%B3%E7%94%9F%E4%B8%BA%E4%BA%A4%E7%A4%BE%E4%BF%9D%E8%A2%AB%E8%B4%9F%E5%80%BA200%E4%B8%87"
    },
    {
      "id": "a8dc060eb06a03dfdd8e86f7c4ea17e4",
      "title": "上门喂猫一小时没找到客户",
      "hot": 3120000,
      "url": "https://so.sina.cn/search/list.d.html?keyword=%E4%B8%8A%E9%97%A8%E5%96%82%E7%8C%AB%E4%B8%80%E5%B0%8F%E6%97%B6%E6%B2%A1%E6%89%BE%E5%88%B0%E5%AE%A2%E6%88%B7",
      "mobileUrl": "https://so.sina.cn/search/list.d.html?keyword=%E4%B8%8A%E9%97%A8%E5%96%82%E7%8C%AB%E4%B8%80%E5%B0%8F%E6%97%B6%E6%B2%A1%E6%89%BE%E5%88%B0%E5%AE%A2%E6%88%B7"
    },
    {
      "id": "9ae592ba7d4218a1451c4b956f713a12",
      "title": "26名路人四面八方跑来救人",
      "hot": 2950000,
      "url": "https://so.sina.cn/search/list.d.html?keyword=26%E5%90%8D%E8%B7%AF%E4%BA%BA%E5%9B%9B%E9%9D%A2%E5%85%AB%E6%96%B9%E8%B7%91%E6%9D%A5%E6%95%91%E4%BA%BA",
      "mobileUrl": "https://so.sina.cn/search/list.d.html?keyword=26%E5%90%8D%E8%B7%AF%E4%BA%BA%E5%9B%9B%E9%9D%A2%E5%85%AB%E6%96%B9%E8%B7%91%E6%9D%A5%E6%95%91%E4%BA%BA"
    },
    {
      "id": "cd999c9b137895aafca85af0ae3645fc",
      "title": "中联重科辟谣：“别停摩托车男子”非公司员工",
      "hot": 2900000,
      "url": "https://k.sina.com.cn/article_1651428902_626ece2602001chjq.html?from=news&subch=onews",
      "mobileUrl": "https://k.sina.com.cn/article_1651428902_626ece2602001chjq.html?from=news&subch=onews"
    },
    {
      "id": "0739d9134e1d8ecf4bbd9c7b7b1ddff7",
      "title": "印度两兄弟同娶一新娘",
      "hot": 2890000,
      "url": "https://so.sina.cn/search/list.d.html?keyword=%E5%8D%B0%E5%BA%A6%E4%B8%A4%E5%85%84%E5%BC%9F%E5%90%8C%E5%A8%B6%E4%B8%80%E6%96%B0%E5%A8%98",
      "mobileUrl": "https://so.sina.cn/search/list.d.html?keyword=%E5%8D%B0%E5%BA%A6%E4%B8%A4%E5%85%84%E5%BC%9F%E5%90%8C%E5%A8%B6%E4%B8%80%E6%96%B0%E5%A8%98"
    },
    {
      "id": "8f3a488785a2c6fcf1dff5f7c412bbd3",
      "title": "台风路径",
      "hot": 2860000,
      "url": "https://so.sina.cn/search/list.d.html?keyword=%E5%8F%B0%E9%A3%8E%E8%B7%AF%E5%BE%84",
      "mobileUrl": "https://so.sina.cn/search/list.d.html?keyword=%E5%8F%B0%E9%A3%8E%E8%B7%AF%E5%BE%84"
    },
    {
      "id": "a178de8dc431dd57e3238834ade1c755",
      "title": "特朗普开始审查马斯克公司合同",
      "hot": 2860000,
      "url": "https://so.sina.cn/search/list.d.html?keyword=%E7%89%B9%E6%9C%97%E6%99%AE%E5%BC%80%E5%A7%8B%E5%AE%A1%E6%9F%A5%E9%A9%AC%E6%96%AF%E5%85%8B%E5%85%AC%E5%8F%B8%E5%90%88%E5%90%8C",
      "mobileUrl": "https://so.sina.cn/search/list.d.html?keyword=%E7%89%B9%E6%9C%97%E6%99%AE%E5%BC%80%E5%A7%8B%E5%AE%A1%E6%9F%A5%E9%A9%AC%E6%96%AF%E5%85%8B%E5%85%AC%E5%8F%B8%E5%90%88%E5%90%8C"
    },
    {
      "id": "83277bfe3def3d697d153c28c1c34028",
      "title": "日本首相石破茂坚持留任",
      "hot": 2800000,
      "url": "https://so.sina.cn/search/list.d.html?keyword=%E6%97%A5%E6%9C%AC%E9%A6%96%E7%9B%B8%E7%9F%B3%E7%A0%B4%E8%8C%82%E5%9D%9A%E6%8C%81%E7%95%99%E4%BB%BB",
      "mobileUrl": "https://so.sina.cn/search/list.d.html?keyword=%E6%97%A5%E6%9C%AC%E9%A6%96%E7%9B%B8%E7%9F%B3%E7%A0%B4%E8%8C%82%E5%9D%9A%E6%8C%81%E7%95%99%E4%BB%BB"
    },
    {
      "id": "4be5132927895cb89d6faca44b476a13",
      "title": "十余省区市雨雨雨",
      "hot": 2800000,
      "url": "https://so.sina.cn/search/list.d.html?keyword=%E5%8D%81%E4%BD%99%E7%9C%81%E5%8C%BA%E5%B8%82%E9%9B%A8%E9%9B%A8%E9%9B%A8",
      "mobileUrl": "https://so.sina.cn/search/list.d.html?keyword=%E5%8D%81%E4%BD%99%E7%9C%81%E5%8C%BA%E5%B8%82%E9%9B%A8%E9%9B%A8%E9%9B%A8"
    },
    {
      "id": "10db0d67c0baf5408431563e412ae3b8",
      "title": "基建狂魔在建世界第一高桥带电梯",
      "hot": 2760000,
      "url": "https://so.sina.cn/search/list.d.html?keyword=%E5%9F%BA%E5%BB%BA%E7%8B%82%E9%AD%94%E5%9C%A8%E5%BB%BA%E4%B8%96%E7%95%8C%E7%AC%AC%E4%B8%80%E9%AB%98%E6%A1%A5%E5%B8%A6%E7%94%B5%E6%A2%AF",
      "mobileUrl": "https://so.sina.cn/search/list.d.html?keyword=%E5%9F%BA%E5%BB%BA%E7%8B%82%E9%AD%94%E5%9C%A8%E5%BB%BA%E4%B8%96%E7%95%8C%E7%AC%AC%E4%B8%80%E9%AB%98%E6%A1%A5%E5%B8%A6%E7%94%B5%E6%A2%AF"
    },
    {
      "id": "04339c93f87ae5c7f5b8088535646762",
      "title": "卢旺达国防部长站军姿",
      "hot": 2720000,
      "url": "https://so.sina.cn/search/list.d.html?keyword=%E5%8D%A2%E6%97%BA%E8%BE%BE%E5%9B%BD%E9%98%B2%E9%83%A8%E9%95%BF%E7%AB%99%E5%86%9B%E5%A7%BF",
      "mobileUrl": "https://so.sina.cn/search/list.d.html?keyword=%E5%8D%A2%E6%97%BA%E8%BE%BE%E5%9B%BD%E9%98%B2%E9%83%A8%E9%95%BF%E7%AB%99%E5%86%9B%E5%A7%BF"
    },
    {
      "id": "35a9c1d4beaf899683c125a172de4d97",
      "title": "台风韦帕即将影响湖北",
      "hot": 2720000,
      "url": "https://so.sina.cn/search/list.d.html?keyword=%E5%8F%B0%E9%A3%8E%E9%9F%A6%E5%B8%95%E5%8D%B3%E5%B0%86%E5%BD%B1%E5%93%8D%E6%B9%96%E5%8C%97",
      "mobileUrl": "https://so.sina.cn/search/list.d.html?keyword=%E5%8F%B0%E9%A3%8E%E9%9F%A6%E5%B8%95%E5%8D%B3%E5%B0%86%E5%BD%B1%E5%93%8D%E6%B9%96%E5%8C%97"
    },
    {
      "id": "167d2067e0e83e7a39605ec29b7867f2",
      "title": "你的英语在外国人眼中的样子",
      "hot": 2710000,
      "url": "https://so.sina.cn/search/list.d.html?keyword=%E4%BD%A0%E7%9A%84%E8%8B%B1%E8%AF%AD%E5%9C%A8%E5%A4%96%E5%9B%BD%E4%BA%BA%E7%9C%BC%E4%B8%AD%E7%9A%84%E6%A0%B7%E5%AD%90",
      "mobileUrl": "https://so.sina.cn/search/list.d.html?keyword=%E4%BD%A0%E7%9A%84%E8%8B%B1%E8%AF%AD%E5%9C%A8%E5%A4%96%E5%9B%BD%E4%BA%BA%E7%9C%BC%E4%B8%AD%E7%9A%84%E6%A0%B7%E5%AD%90"
    },
    {
      "id": "d2a6b9d75dd5042f4095987a34797a69",
      "title": "731部队成员称解剖了活人300名",
      "hot": 2630000,
      "url": "https://so.sina.cn/search/list.d.html?keyword=731%E9%83%A8%E9%98%9F%E6%88%90%E5%91%98%E7%A7%B0%E8%A7%A3%E5%89%96%E4%BA%86%E6%B4%BB%E4%BA%BA300%E5%90%8D",
      "mobileUrl": "https://so.sina.cn/search/list.d.html?keyword=731%E9%83%A8%E9%98%9F%E6%88%90%E5%91%98%E7%A7%B0%E8%A7%A3%E5%89%96%E4%BA%86%E6%B4%BB%E4%BA%BA300%E5%90%8D"
    },
    {
      "id": "9ae1d9f43feb0568fdf2ad244b6f483b",
      "title": "朝雪录云合22.8%",
      "hot": 2630000,
      "url": "https://so.sina.cn/search/list.d.html?keyword=%E6%9C%9D%E9%9B%AA%E5%BD%95%E4%BA%91%E5%90%8822.8%25",
      "mobileUrl": "https://so.sina.cn/search/list.d.html?keyword=%E6%9C%9D%E9%9B%AA%E5%BD%95%E4%BA%91%E5%90%8822.8%25"
    },
    {
      "id": "3a79abfed6c2e38acb4a06443783ee7d",
      "title": "黄仁勋再谈小米华为",
      "hot": 2620000,
      "url": "https://so.sina.cn/search/list.d.html?keyword=%E9%BB%84%E4%BB%81%E5%8B%8B%E5%86%8D%E8%B0%88%E5%B0%8F%E7%B1%B3%E5%8D%8E%E4%B8%BA",
      "mobileUrl": "https://so.sina.cn/search/list.d.html?keyword=%E9%BB%84%E4%BB%81%E5%8B%8B%E5%86%8D%E8%B0%88%E5%B0%8F%E7%B1%B3%E5%8D%8E%E4%B8%BA"
    }
  ]
}