{
  "meta": {
    "platform": "bilibili",
    "date": "2026-04-27T02:47:34.542805",
    "count": 20
  },
  "data": [
    {
      "id": "BV1AHo5B9Ejs",
      "title": "宝岛珠还，功成无我",
      "desc": "该视频暂无简介",
      "cover": "https://i1.hdslb.com/bfs/archive/5464463af818f03cf723b0a732687066e6e9c047.jpg",
      "author": "朱铁雄",
      "timestamp": null,
      "hot": 5264,
      "url": "https://www.bilibili.com/video/BV1AHo5B9Ejs",
      "mobileUrl": "https://m.bilibili.com/video/BV1AHo5B9Ejs"
    },
    {
      "id": "BV16ooQBsERA",
      "title": "对不起...",
      "desc": "该视频暂无简介",
      "cover": "https://i0.hdslb.com/bfs/archive/e4dab2ecf008f3e0aaf6bc802a4127d8e09f0418.jpg",
      "author": "逗比的雀巢",
      "timestamp": null,
      "hot": 9886,
      "url": "https://www.bilibili.com/video/BV16ooQBsERA",
      "mobileUrl": "https://m.bilibili.com/video/BV16ooQBsERA"
    },
    {
      "id": "BV1BtoYBaELd",
      "title": "《原神》幕后的故事：向至冬，向未来",
      "desc": "该视频暂无简介",
      "cover": "https://i0.hdslb.com/bfs/archive/229cf8a1a722704ac25f6c38070e5b50c16cf834.jpg",
      "author": "原神",
      "timestamp": null,
      "hot": 52485,
      "url": "https://www.bilibili.com/video/BV1BtoYBaELd",
      "mobileUrl": "https://m.bilibili.com/video/BV1BtoYBaELd"
    },
    {
      "id": "BV1TFo7BiE11",
      "title": "【星穹铁道生日会】二相乐园躲猫猫大赛！！",
      "desc": "该视频暂无简介",
      "cover": "https://i1.hdslb.com/bfs/archive/e522fba990846039ab6c85862f84a18f4c8539ff.jpg",
      "author": "WildKoko木可",
      "timestamp": null,
      "hot": 7710,
      "url": "https://www.bilibili.com/video/BV1TFo7BiE11",
      "mobileUrl": "https://m.bilibili.com/video/BV1TFo7BiE11"
    },
    {
      "id": "BV1dio5BVEve",
      "title": "【星穹铁道生日会】《求索者》天才俱乐部印象曲",
      "desc": "该视频暂无简介",
      "cover": "https://i2.hdslb.com/bfs/archive/5301935c2f0994fbd48402612da18cfc5c43eb91.jpg",
      "author": "帷幕VMovie",
      "timestamp": null,
      "hot": 13313,
      "url": "https://www.bilibili.com/video/BV1dio5BVEve",
      "mobileUrl": "https://m.bilibili.com/video/BV1dio5BVEve"
    },
    {
      "id": "BV1TtoaBCEyz",
      "title": "⚡对 对 子 战 神 4⚡",
      "desc": "该视频暂无简介",
      "cover": "https://i1.hdslb.com/bfs/archive/2b1124c6cbaabdf4bc2467afc3925541021e5c5f.jpg",
      "author": "洛温阿特金森",
      "timestamp": null,
      "hot": 1656,
      "url": "https://www.bilibili.com/video/BV1TtoaBCEyz",
      "mobileUrl": "https://m.bilibili.com/video/BV1TtoaBCEyz"
    },
    {
      "id": "BV1ocoEBQEvr",
      "title": "这个世界上这么讨人嫌，让人想沙的脸居然有两张…《enemy》第二集",
      "desc": "该视频暂无简介",
      "cover": "https://i0.hdslb.com/bfs/archive/c84c76c9168d7b581c9d1279cb3cbf391b11f9c8.jpg",
      "author": "煎饼果仔呀",
      "timestamp": null,
      "hot": 1377,
      "url": "https://www.bilibili.com/video/BV1ocoEBQEvr",
      "mobileUrl": "https://m.bilibili.com/video/BV1ocoEBQEvr"
    },
    {
      "id": "BV1aBoYBREyj",
      "title": "如何在亚马逊雨林里种树？【硬核狠人88】",
      "desc": "该视频暂无简介",
      "cover": "https://i0.hdslb.com/bfs/archive/268b3302092bd9676f4205048de0108ba04772ff.jpg",
      "author": "小约翰可汗",
      "timestamp": null,
      "hot": 17490,
      "url": "https://www.bilibili.com/video/BV1aBoYBREyj",
      "mobileUrl": "https://m.bilibili.com/video/BV1aBoYBREyj"
    },
    {
      "id": "BV1MXo5BYEsV",
      "title": "当你长大当了音乐老师后",
      "desc": "该视频暂无简介",
      "cover": "https://i2.hdslb.com/bfs/archive/8e50c14d53c665376551a8a7c861e1f4c3fcf071.jpg",
      "author": "喜欢打树叶",
      "timestamp": null,
      "hot": 764,
      "url": "https://www.bilibili.com/video/BV1MXo5BYEsV",
      "mobileUrl": "https://m.bilibili.com/video/BV1MXo5BYEsV"
    },
    {
      "id": "BV19DoEBJEJj",
      "title": "【星穹铁道生日会】星穹拾光 Pieces Of Miracles",
      "desc": "该视频暂无简介",
      "cover": "https://i2.hdslb.com/bfs/archive/0fb47d4c24e42062a28dbdf457e4c7cd8210a62e.jpg",
      "author": "哈米伦的弄笛者",
      "timestamp": null,
      "hot": 5386,
      "url": "https://www.bilibili.com/video/BV19DoEBJEJj",
      "mobileUrl": "https://m.bilibili.com/video/BV19DoEBJEJj"
    },
    {
      "id": "BV1gdoTB7EFd",
      "title": "45岁派出所所长执勤中不幸牺牲，从辅警到所长，他用25年走完忠诚之路！",
      "desc": "该视频暂无简介",
      "cover": "https://i0.hdslb.com/bfs/archive/561ce39851a6fd08557d256ff04fde84a04c0907.jpg",
      "author": "人民日报",
      "timestamp": null,
      "hot": 16292,
      "url": "https://www.bilibili.com/video/BV1gdoTB7EFd",
      "mobileUrl": "https://m.bilibili.com/video/BV1gdoTB7EFd"
    },
    {
      "id": "BV1W2oSBWEYw",
      "title": "在桌底埋伏时发生这种事我也不想的啊！！",
      "desc": "该视频暂无简介",
      "cover": "https://i0.hdslb.com/bfs/archive/d8e1f57bbffdee83526700f074290b5c81df39ea.jpg",
      "author": "煤花三",
      "timestamp": null,
      "hot": 1646,
      "url": "https://www.bilibili.com/video/BV1W2oSBWEYw",
      "mobileUrl": "https://m.bilibili.com/video/BV1W2oSBWEYw"
    },
    {
      "id": "BV16poGBLEbZ",
      "title": "无公司，无投资，无AI！我们手搓了一个原创中恐无限流大电影！？",
      "desc": "该视频暂无简介",
      "cover": "https://i0.hdslb.com/bfs/archive/841a75603754b9108d8512f5483914270c26c7ed.jpg",
      "author": "爱黏人的圆子哔___",
      "timestamp": null,
      "hot": 10467,
      "url": "https://www.bilibili.com/video/BV16poGBLEbZ",
      "mobileUrl": "https://m.bilibili.com/video/BV16poGBLEbZ"
    },
    {
      "id": "BV12XoGB9Ecx",
      "title": "【星穹铁道生日会】别笑，你也过不了第二关！",
      "desc": "该视频暂无简介",
      "cover": "https://i2.hdslb.com/bfs/archive/95e1f48dceaf745919adc4e36f67c2e585f9fdc7.jpg",
      "author": "一万根韭菜",
      "timestamp": null,
      "hot": 6640,
      "url": "https://www.bilibili.com/video/BV12XoGB9Ecx",
      "mobileUrl": "https://m.bilibili.com/video/BV12XoGB9Ecx"
    },
    {
      "id": "BV1hEoXBgEPd",
      "title": "以防你不知道异环里可以强行让早雾喝酒",
      "desc": "该视频暂无简介",
      "cover": "https://i1.hdslb.com/bfs/archive/ecfeef175fa8304c6105e379dfd711baf3acf080.jpg",
      "author": "不爱说话的紫叶",
      "timestamp": null,
      "hot": 6570,
      "url": "https://www.bilibili.com/video/BV1hEoXBgEPd",
      "mobileUrl": "https://m.bilibili.com/video/BV1hEoXBgEPd"
    },
    {
      "id": "BV1UeoSBaEYZ",
      "title": "《明日方舟》七周年庆典活动宣传PV",
      "desc": "该视频暂无简介",
      "cover": "https://i0.hdslb.com/bfs/archive/3ac83de9c1f4c46f9018b95908fae49c685f8e47.jpg",
      "author": "明日方舟",
      "timestamp": null,
      "hot": 16022,
      "url": "https://www.bilibili.com/video/BV1UeoSBaEYZ",
      "mobileUrl": "https://m.bilibili.com/video/BV1UeoSBaEYZ"
    },
    {
      "id": "BV12ZoxBZE6H",
      "title": "你可以熬夜，但第二天必须去做这些恢复。",
      "desc": "该视频暂无简介",
      "cover": "https://i2.hdslb.com/bfs/archive/d3823e631d24fbdac3f00017cd937581cef03294.jpg",
      "author": "心理能量1101",
      "timestamp": null,
      "hot": 583,
      "url": "https://www.bilibili.com/video/BV12ZoxBZE6H",
      "mobileUrl": "https://m.bilibili.com/video/BV12ZoxBZE6H"
    },
    {
      "id": "BV1PZdBBWEbD",
      "title": "《归环》概念片 ：回响",
      "desc": "该视频暂无简介",
      "cover": "https://i1.hdslb.com/bfs/archive/ca9eafa0b7ea302959d9114b4498bb927be0c860.jpg",
      "author": "归环",
      "timestamp": null,
      "hot": 2645,
      "url": "https://www.bilibili.com/video/BV1PZdBBWEbD",
      "mobileUrl": "https://m.bilibili.com/video/BV1PZdBBWEbD"
    },
    {
      "id": "BV1Fjo7BREFm",
      "title": "来不及哀悼立刻赶往清波寨【动画】",
      "desc": "该视频暂无简介",
      "cover": "https://i2.hdslb.com/bfs/archive/b04ed81d8ba058d43b8a47309652e2c0f6195955.jpg",
      "author": "越with霓虹鸡",
      "timestamp": null,
      "hot": 977,
      "url": "https://www.bilibili.com/video/BV1Fjo7BREFm",
      "mobileUrl": "https://m.bilibili.com/video/BV1Fjo7BREFm"
    },
    {
      "id": "BV1HDo7BhE1u",
      "title": "泽连斯基有牌打了",
      "desc": "该视频暂无简介",
      "cover": "https://i1.hdslb.com/bfs/archive/7eb89ff648d6d1aa0266bb50e766c419611214c0.jpg",
      "author": "燕三嘤嘤嘤",
      "timestamp": null,
      "hot": 10258,
      "url": "https://www.bilibili.com/video/BV1HDo7BhE1u",
      "mobileUrl": "https://m.bilibili.com/video/BV1HDo7BhE1u"
    }
  ]
}