{
  "meta": {
    "platform": "sina",
    "date": "2026-02-25T02:09:24.354980",
    "count": 20
  },
  "data": [
    {
      "id": "49129d84fdd76f4a0e384eb21b56a9bb",
      "title": "美军11架F22战机抵达以色列",
      "desc": null,
      "author": null,
      "timestamp": null,
      "hot": 4300000,
      "url": "https://so.sina.cn/search/list.d.html?keyword=%E7%BE%8E%E5%86%9B11%E6%9E%B6F22%E6%88%98%E6%9C%BA%E6%8A%B5%E8%BE%BE%E4%BB%A5%E8%89%B2%E5%88%97",
      "mobileUrl": "https://so.sina.cn/search/list.d.html?keyword=%E7%BE%8E%E5%86%9B11%E6%9E%B6F22%E6%88%98%E6%9C%BA%E6%8A%B5%E8%BE%BE%E4%BB%A5%E8%89%B2%E5%88%97"
    },
    {
      "id": "9fc9a268bc730750da998941deffea9b",
      "title": "女子返程堵车偶遇10年未见初恋",
      "desc": null,
      "author": null,
      "timestamp": null,
      "hot": 4000000,
      "url": "https://so.sina.cn/search/list.d.html?keyword=%E5%A5%B3%E5%AD%90%E8%BF%94%E7%A8%8B%E5%A0%B5%E8%BD%A6%E5%81%B6%E9%81%8710%E5%B9%B4%E6%9C%AA%E8%A7%81%E5%88%9D%E6%81%8B",
      "mobileUrl": "https://so.sina.cn/search/list.d.html?keyword=%E5%A5%B3%E5%AD%90%E8%BF%94%E7%A8%8B%E5%A0%B5%E8%BD%A6%E5%81%B6%E9%81%8710%E5%B9%B4%E6%9C%AA%E8%A7%81%E5%88%9D%E6%81%8B"
    },
    {
      "id": "faa7ec18ecfd5ab2338dac72efc6d367",
      "title": "九组数据感受万马奔腾的活力春节",
      "desc": null,
      "author": null,
      "timestamp": null,
      "hot": 3620000,
      "url": "https://so.sina.cn/search/list.d.html?keyword=%E4%B9%9D%E7%BB%84%E6%95%B0%E6%8D%AE%E6%84%9F%E5%8F%97%E4%B8%87%E9%A9%AC%E5%A5%94%E8%85%BE%E7%9A%84%E6%B4%BB%E5%8A%9B%E6%98%A5%E8%8A%82",
      "mobileUrl": "https://so.sina.cn/search/list.d.html?keyword=%E4%B9%9D%E7%BB%84%E6%95%B0%E6%8D%AE%E6%84%9F%E5%8F%97%E4%B8%87%E9%A9%AC%E5%A5%94%E8%85%BE%E7%9A%84%E6%B4%BB%E5%8A%9B%E6%98%A5%E8%8A%82"
    },
    {
      "id": "350ce006ae5762e6215d6fd4d4fe12df",
      "title": "女子在加油站人肉插队躺后车引擎盖",
      "desc": null,
      "author": null,
      "timestamp": null,
      "hot": 3340000,
      "url": "https://so.sina.cn/search/list.d.html?keyword=%E5%A5%B3%E5%AD%90%E5%9C%A8%E5%8A%A0%E6%B2%B9%E7%AB%99%E4%BA%BA%E8%82%89%E6%8F%92%E9%98%9F%E8%BA%BA%E5%90%8E%E8%BD%A6%E5%BC%95%E6%93%8E%E7%9B%96",
      "mobileUrl": "https://so.sina.cn/search/list.d.html?keyword=%E5%A5%B3%E5%AD%90%E5%9C%A8%E5%8A%A0%E6%B2%B9%E7%AB%99%E4%BA%BA%E8%82%89%E6%8F%92%E9%98%9F%E8%BA%BA%E5%90%8E%E8%BD%A6%E5%BC%95%E6%93%8E%E7%9B%96"
    },
    {
      "id": "b5d5fd1dcac40978c5cf1480d3d5ad7e",
      "title": "宝马7系降价约27万",
      "desc": null,
      "author": null,
      "timestamp": null,
      "hot": 3040000,
      "url": "https://so.sina.cn/search/list.d.html?keyword=%E5%AE%9D%E9%A9%AC7%E7%B3%BB%E9%99%8D%E4%BB%B7%E7%BA%A627%E4%B8%87",
      "mobileUrl": "https://so.sina.cn/search/list.d.html?keyword=%E5%AE%9D%E9%A9%AC7%E7%B3%BB%E9%99%8D%E4%BB%B7%E7%BA%A627%E4%B8%87"
    },
    {
      "id": "74050555577602c7fe56770ce9e92ec3",
      "title": "不内耗的人脑子里是这样想的",
      "desc": null,
      "author": null,
      "timestamp": null,
      "hot": 2780000,
      "url": "https://so.sina.cn/search/list.d.html?keyword=%E4%B8%8D%E5%86%85%E8%80%97%E7%9A%84%E4%BA%BA%E8%84%91%E5%AD%90%E9%87%8C%E6%98%AF%E8%BF%99%E6%A0%B7%E6%83%B3%E7%9A%84",
      "mobileUrl": "https://so.sina.cn/search/list.d.html?keyword=%E4%B8%8D%E5%86%85%E8%80%97%E7%9A%84%E4%BA%BA%E8%84%91%E5%AD%90%E9%87%8C%E6%98%AF%E8%BF%99%E6%A0%B7%E6%83%B3%E7%9A%84"
    },
    {
      "id": "2ef9b71c8206a1704d6de633755e6f1f",
      "title": "专家在香港发现文物证实夏朝存在",
      "desc": null,
      "author": null,
      "timestamp": null,
      "hot": 2770000,
      "url": "https://so.sina.cn/search/list.d.html?keyword=%E4%B8%93%E5%AE%B6%E5%9C%A8%E9%A6%99%E6%B8%AF%E5%8F%91%E7%8E%B0%E6%96%87%E7%89%A9%E8%AF%81%E5%AE%9E%E5%A4%8F%E6%9C%9D%E5%AD%98%E5%9C%A8",
      "mobileUrl": "https://so.sina.cn/search/list.d.html?keyword=%E4%B8%93%E5%AE%B6%E5%9C%A8%E9%A6%99%E6%B8%AF%E5%8F%91%E7%8E%B0%E6%96%87%E7%89%A9%E8%AF%81%E5%AE%9E%E5%A4%8F%E6%9C%9D%E5%AD%98%E5%9C%A8"
    },
    {
      "id": "2da9a76da23c7839d747bc17b78140c0",
      "title": "头孢停药三天能饮酒？辟谣",
      "desc": null,
      "author": null,
      "timestamp": null,
      "hot": 2730000,
      "url": "https://k.sina.com.cn/article_1841812881_6dc7d59102001nph8.html?from=society",
      "mobileUrl": "https://k.sina.com.cn/article_1841812881_6dc7d59102001nph8.html?from=society"
    },
    {
      "id": "e7fe0f504faf9b051d59962413a7e2c5",
      "title": "王楚钦鹰眼挑战失败",
      "desc": null,
      "author": null,
      "timestamp": null,
      "hot": 2720000,
      "url": "https://so.sina.cn/search/list.d.html?keyword=%E7%8E%8B%E6%A5%9A%E9%92%A6%E9%B9%B0%E7%9C%BC%E6%8C%91%E6%88%98%E5%A4%B1%E8%B4%A5",
      "mobileUrl": "https://so.sina.cn/search/list.d.html?keyword=%E7%8E%8B%E6%A5%9A%E9%92%A6%E9%B9%B0%E7%9C%BC%E6%8C%91%E6%88%98%E5%A4%B1%E8%B4%A5"
    },
    {
      "id": "4dc9561ef1ca4ab6e905ed21f4d45af9",
      "title": "伊能静尝试生酮饮食半年瘦到86斤",
      "desc": null,
      "author": null,
      "timestamp": null,
      "hot": 2710000,
      "url": "https://so.sina.cn/search/list.d.html?keyword=%E4%BC%8A%E8%83%BD%E9%9D%99%E5%B0%9D%E8%AF%95%E7%94%9F%E9%85%AE%E9%A5%AE%E9%A3%9F%E5%8D%8A%E5%B9%B4%E7%98%A6%E5%88%B086%E6%96%A4",
      "mobileUrl": "https://so.sina.cn/search/list.d.html?keyword=%E4%BC%8A%E8%83%BD%E9%9D%99%E5%B0%9D%E8%AF%95%E7%94%9F%E9%85%AE%E9%A5%AE%E9%A3%9F%E5%8D%8A%E5%B9%B4%E7%98%A6%E5%88%B086%E6%96%A4"
    },
    {
      "id": "77a3126115e367e883dc24367bbfda86",
      "title": "牛奶灌溉草莓卖出360元天价",
      "desc": null,
      "author": null,
      "timestamp": null,
      "hot": 2710000,
      "url": "https://so.sina.cn/search/list.d.html?keyword=%E7%89%9B%E5%A5%B6%E7%81%8C%E6%BA%89%E8%8D%89%E8%8E%93%E5%8D%96%E5%87%BA360%E5%85%83%E5%A4%A9%E4%BB%B7",
      "mobileUrl": "https://so.sina.cn/search/list.d.html?keyword=%E7%89%9B%E5%A5%B6%E7%81%8C%E6%BA%89%E8%8D%89%E8%8E%93%E5%8D%96%E5%87%BA360%E5%85%83%E5%A4%A9%E4%BB%B7"
    },
    {
      "id": "532918bf0e3e726025ad986fe419ea06",
      "title": "用4年感受到了命运的推背感",
      "desc": null,
      "author": null,
      "timestamp": null,
      "hot": 2680000,
      "url": "https://so.sina.cn/search/list.d.html?keyword=%E7%94%A84%E5%B9%B4%E6%84%9F%E5%8F%97%E5%88%B0%E4%BA%86%E5%91%BD%E8%BF%90%E7%9A%84%E6%8E%A8%E8%83%8C%E6%84%9F",
      "mobileUrl": "https://so.sina.cn/search/list.d.html?keyword=%E7%94%A84%E5%B9%B4%E6%84%9F%E5%8F%97%E5%88%B0%E4%BA%86%E5%91%BD%E8%BF%90%E7%9A%84%E6%8E%A8%E8%83%8C%E6%84%9F"
    },
    {
      "id": "ba2761f6328b120cac32c4ee2f64cee6",
      "title": "iPhone18Pro深红色",
      "desc": null,
      "author": null,
      "timestamp": null,
      "hot": 2660000,
      "url": "https://so.sina.cn/search/list.d.html?keyword=iPhone18Pro%E6%B7%B1%E7%BA%A2%E8%89%B2",
      "mobileUrl": "https://so.sina.cn/search/list.d.html?keyword=iPhone18Pro%E6%B7%B1%E7%BA%A2%E8%89%B2"
    },
    {
      "id": "bb9fc68b89788ae91aa50949259ede28",
      "title": "台北餐厅冷库女尸案",
      "desc": null,
      "author": null,
      "timestamp": null,
      "hot": 2660000,
      "url": "https://so.sina.cn/search/list.d.html?keyword=%E5%8F%B0%E5%8C%97%E9%A4%90%E5%8E%85%E5%86%B7%E5%BA%93%E5%A5%B3%E5%B0%B8%E6%A1%88",
      "mobileUrl": "https://so.sina.cn/search/list.d.html?keyword=%E5%8F%B0%E5%8C%97%E9%A4%90%E5%8E%85%E5%86%B7%E5%BA%93%E5%A5%B3%E5%B0%B8%E6%A1%88"
    },
    {
      "id": "aca703c45e0bf24285eb3590bee1b26d",
      "title": "男子服务区捡走千元红包该不该拿走",
      "desc": null,
      "author": null,
      "timestamp": null,
      "hot": 2560000,
      "url": "https://so.sina.cn/search/list.d.html?keyword=%E7%94%B7%E5%AD%90%E6%9C%8D%E5%8A%A1%E5%8C%BA%E6%8D%A1%E8%B5%B0%E5%8D%83%E5%85%83%E7%BA%A2%E5%8C%85%E8%AF%A5%E4%B8%8D%E8%AF%A5%E6%8B%BF%E8%B5%B0",
      "mobileUrl": "https://so.sina.cn/search/list.d.html?keyword=%E7%94%B7%E5%AD%90%E6%9C%8D%E5%8A%A1%E5%8C%BA%E6%8D%A1%E8%B5%B0%E5%8D%83%E5%85%83%E7%BA%A2%E5%8C%85%E8%AF%A5%E4%B8%8D%E8%AF%A5%E6%8B%BF%E8%B5%B0"
    },
    {
      "id": "ec105c7bbb947067bc359f16dd923717",
      "title": "原神 开门",
      "desc": null,
      "author": null,
      "timestamp": null,
      "hot": 2530000,
      "url": "https://so.sina.cn/search/list.d.html?keyword=%E5%8E%9F%E7%A5%9E%20%E5%BC%80%E9%97%A8",
      "mobileUrl": "https://so.sina.cn/search/list.d.html?keyword=%E5%8E%9F%E7%A5%9E%20%E5%BC%80%E9%97%A8"
    },
    {
      "id": "01d9ec194b0d4b34289f29599b2a6868",
      "title": "西安一市民除夕夜被AI给骂了",
      "desc": null,
      "author": null,
      "timestamp": null,
      "hot": 2530000,
      "url": "https://so.sina.cn/search/list.d.html?keyword=%E8%A5%BF%E5%AE%89%E4%B8%80%E5%B8%82%E6%B0%91%E9%99%A4%E5%A4%95%E5%A4%9C%E8%A2%ABAI%E7%BB%99%E9%AA%82%E4%BA%86",
      "mobileUrl": "https://so.sina.cn/search/list.d.html?keyword=%E8%A5%BF%E5%AE%89%E4%B8%80%E5%B8%82%E6%B0%91%E9%99%A4%E5%A4%95%E5%A4%9C%E8%A2%ABAI%E7%BB%99%E9%AA%82%E4%BA%86"
    },
    {
      "id": "e0c3e8fab1424002d110d1d4923a2db8",
      "title": "掉在床缝里的物品有救了",
      "desc": null,
      "author": null,
      "timestamp": null,
      "hot": 2530000,
      "url": "https://so.sina.cn/search/list.d.html?keyword=%E6%8E%89%E5%9C%A8%E5%BA%8A%E7%BC%9D%E9%87%8C%E7%9A%84%E7%89%A9%E5%93%81%E6%9C%89%E6%95%91%E4%BA%86",
      "mobileUrl": "https://so.sina.cn/search/list.d.html?keyword=%E6%8E%89%E5%9C%A8%E5%BA%8A%E7%BC%9D%E9%87%8C%E7%9A%84%E7%89%A9%E5%93%81%E6%9C%89%E6%95%91%E4%BA%86"
    },
    {
      "id": "283dbd86a723f62eae0455f08a7a3a4d",
      "title": "谷爱凌妈妈谷燕的人生轨迹",
      "desc": null,
      "author": null,
      "timestamp": null,
      "hot": 2530000,
      "url": "https://so.sina.cn/search/list.d.html?keyword=%E8%B0%B7%E7%88%B1%E5%87%8C%E5%A6%88%E5%A6%88%E8%B0%B7%E7%87%95%E7%9A%84%E4%BA%BA%E7%94%9F%E8%BD%A8%E8%BF%B9",
      "mobileUrl": "https://so.sina.cn/search/list.d.html?keyword=%E8%B0%B7%E7%88%B1%E5%87%8C%E5%A6%88%E5%A6%88%E8%B0%B7%E7%87%95%E7%9A%84%E4%BA%BA%E7%94%9F%E8%BD%A8%E8%BF%B9"
    },
    {
      "id": "8f242fabbebb95d105aa60f861d6fdb4",
      "title": "惊蛰无声",
      "desc": null,
      "author": null,
      "timestamp": null,
      "hot": 1780000,
      "url": "https://so.sina.cn/search/list.d.html?keyword=%E6%83%8A%E8%9B%B0%E6%97%A0%E5%A3%B0",
      "mobileUrl": "https://so.sina.cn/search/list.d.html?keyword=%E6%83%8A%E8%9B%B0%E6%97%A0%E5%A3%B0"
    }
  ]
}