{
  "meta": {
    "platform": "thepaper",
    "date": "2025-06-30T01:45:26.631640",
    "count": 20
  },
  "data": [
    {
      "id": "31061140",
      "title": "环海南岛摩旅被私家车逼停？儋州交警发布情况通报",
      "cover": "https://imgpai.thepaper.cn/newpai/image/1751163383447_XRxX8A_1751163383617.png",
      "hot": 278,
      "timestamp": 1751166743473,
      "url": "https://www.thepaper.cn/newsDetail_forward_31061140",
      "mobileUrl": "https://m.thepaper.cn/newsDetail_forward_31061140"
    },
    {
      "id": "29537315",
      "title": "特稿｜数十亿投资沦为“全国古镇连锁”，“沉睡古城”如何盘活？",
      "cover": "https://imagecloud.thepaper.cn/thepaper/image/332/216/374.jpg",
      "hot": 714,
      "timestamp": 1751194747695,
      "url": "https://www.thepaper.cn/newsDetail_forward_29537315",
      "mobileUrl": "https://m.thepaper.cn/newsDetail_forward_29537315"
    },
    {
      "id": "31062501",
      "title": "“路易号”亮相后首个周末：“大船”开进人海，商圈一片火热",
      "cover": "https://imgpai.thepaper.cn/newpai/image/1751197392517_eJjS3m_1751197392815.png",
      "hot": 304,
      "timestamp": 1751202434345,
      "url": "https://www.thepaper.cn/newsDetail_forward_31062501",
      "mobileUrl": "https://m.thepaper.cn/newsDetail_forward_31062501"
    },
    {
      "id": "31061176",
      "title": "视频丨双机起飞、红外弹出击，歼-16霸气驱离外机影像公布",
      "cover": "https://imgpai.thepaper.cn/newpai/image/1751164635080_id5yx3_1751164635469.png",
      "hot": 486,
      "timestamp": 1751165355972,
      "url": "https://www.thepaper.cn/newsDetail_forward_31061176",
      "mobileUrl": "https://m.thepaper.cn/newsDetail_forward_31061176"
    },
    {
      "id": "31062964",
      "title": "5岁女童感染“食脑虫”昏迷不醒，这种病原体如何进入人体？有多凶险？",
      "cover": "https://imgpai.thepaper.cn/newpai/image/1751204425981_NPdmix_1751204426199.png",
      "hot": 368,
      "timestamp": 1751207212010,
      "url": "https://www.thepaper.cn/newsDetail_forward_31062964",
      "mobileUrl": "https://m.thepaper.cn/newsDetail_forward_31062964"
    },
    {
      "id": "31063103",
      "title": "“苏超”观众人数仅隔两周破4万大关，17岁高中生球员独中二元",
      "cover": "https://imgpai.thepaper.cn/newpai/image/1751206947106_Q55Cda_1751206947528.png",
      "hot": 157,
      "timestamp": 1751209218286,
      "url": "https://www.thepaper.cn/newsDetail_forward_31063103",
      "mobileUrl": "https://m.thepaper.cn/newsDetail_forward_31063103"
    },
    {
      "id": "31061869",
      "title": "中国稀土多名董事、高管调整引发关注，最新声明：相关人员仍在集团其他岗位任职",
      "cover": "https://imgpai.thepaper.cn/newpai/image/1751180190717_yfszaN_1751180190983.png",
      "hot": 356,
      "timestamp": 1751182277432,
      "url": "https://www.thepaper.cn/newsDetail_forward_31061869",
      "mobileUrl": "https://m.thepaper.cn/newsDetail_forward_31061869"
    },
    {
      "id": "31061272",
      "title": "黄旭华院士今日在家乡广东汕尾安葬",
      "cover": "https://imgpai.thepaper.cn/newpai/image/1751172971745_ynXxGe_1751172971967.png",
      "hot": 817,
      "timestamp": 1751169637668,
      "url": "https://www.thepaper.cn/newsDetail_forward_31061272",
      "mobileUrl": "https://m.thepaper.cn/newsDetail_forward_31061272"
    },
    {
      "id": "31061126",
      "title": "言短意长｜不可轻视凤阳近期多起舆情隐含的深层次问题",
      "cover": "https://imgpai.thepaper.cn/newpai/image/1751162136268_EDp46Y_1751162136729.png",
      "hot": 438,
      "timestamp": 1751164213537,
      "url": "https://www.thepaper.cn/newsDetail_forward_31061126",
      "mobileUrl": "https://m.thepaper.cn/newsDetail_forward_31061126"
    },
    {
      "id": "31061308",
      "title": "创纪录！巴菲特再捐60亿美元伯克希尔股票，总额超600亿美元",
      "cover": "https://imgpai.thepaper.cn/newpai/image/1751170817237_M1k8iM_1751170817423.png",
      "hot": 191,
      "timestamp": 1751176169607,
      "url": "https://www.thepaper.cn/newsDetail_forward_31061308",
      "mobileUrl": "https://m.thepaper.cn/newsDetail_forward_31061308"
    },
    {
      "id": "31061936",
      "title": "小米回应YU7刹车片赛道测试起火：没跑散热圈极端情况下直接驻车，制动系统功能健全",
      "cover": "https://imgpai.thepaper.cn/newpai/image/1751183683298_aAeanb_1751183683542.png",
      "hot": 84,
      "timestamp": 1751189803758,
      "url": "https://www.thepaper.cn/newsDetail_forward_31061936",
      "mobileUrl": "https://m.thepaper.cn/newsDetail_forward_31061936"
    },
    {
      "id": "31061013",
      "title": "中国游客冰岛租车遭天价索赔：沙尘造成“针眼大损伤”要赔14万，新车才23万",
      "cover": "https://imgpai.thepaper.cn/newpai/image/1751159687096_r1ws7h_1751159687311.png",
      "hot": 233,
      "timestamp": 1751163282134,
      "url": "https://www.thepaper.cn/newsDetail_forward_31061013",
      "mobileUrl": "https://m.thepaper.cn/newsDetail_forward_31061013"
    },
    {
      "id": "31062423",
      "title": "国际原子能机构总干事：伊朗先进的核技术不会被军事行动抹去",
      "cover": "https://imgpai.thepaper.cn/newpai/image/1751193342179_y7eZ16_1751193342360.png",
      "hot": 429,
      "timestamp": 1751193757968,
      "url": "https://www.thepaper.cn/newsDetail_forward_31062423",
      "mobileUrl": "https://m.thepaper.cn/newsDetail_forward_31062423"
    },
    {
      "id": "31060933",
      "title": "山东舰航母编队将访问香港，对外开放预约指南来了",
      "cover": "https://imgpai.thepaper.cn/newpai/image/1751158741173_KfDyGS_1751158741366.png",
      "hot": 115,
      "timestamp": 1751159538422,
      "url": "https://www.thepaper.cn/newsDetail_forward_31060933",
      "mobileUrl": "https://m.thepaper.cn/newsDetail_forward_31060933"
    },
    {
      "id": "31061799",
      "title": "乐高乐园再回应“过山车故障”：骑乘设备检测到异常自动停止，已向游客致歉",
      "cover": "https://imgpai.thepaper.cn/newpai/image/1751176640657_n8HZSa_1751176640866.png",
      "hot": 35,
      "timestamp": 1751180972600,
      "url": "https://www.thepaper.cn/newsDetail_forward_31061799",
      "mobileUrl": "https://m.thepaper.cn/newsDetail_forward_31061799"
    },
    {
      "id": "31062824",
      "title": "“苏超”观众人数纪录再刷新，苏州主场观众达43617人",
      "cover": "https://imgpai.thepaper.cn/newpai/image/1751201806680_Ch4C3i_1751201806897.png",
      "hot": 131,
      "timestamp": 1751201826027,
      "url": "https://www.thepaper.cn/newsDetail_forward_31062824",
      "mobileUrl": "https://m.thepaper.cn/newsDetail_forward_31062824"
    },
    {
      "id": "31061953",
      "title": "媒体：冰岛租车“针眼伤”遭14万索赔，到底谁挖的“坑”？",
      "cover": "https://imgpai.thepaper.cn/newpai/image/1751184887523_wYn3Jj_1751184887838.png",
      "hot": 194,
      "timestamp": 1751185411074,
      "url": "https://www.thepaper.cn/newsDetail_forward_31061953",
      "mobileUrl": "https://m.thepaper.cn/newsDetail_forward_31061953"
    },
    {
      "id": "31061164",
      "title": "内塔尼亚胡贪腐案开庭在即，特朗普拿伊朗和加沙给他“辩护”",
      "cover": "https://imgpai.thepaper.cn/newpai/image/1751163986050_f1WefN_1751163986311.png",
      "hot": 252,
      "timestamp": 1751167120267,
      "url": "https://www.thepaper.cn/newsDetail_forward_31061164",
      "mobileUrl": "https://m.thepaper.cn/newsDetail_forward_31061164"
    },
    {
      "id": "31064643",
      "title": "人民日报：一人住院全家忙乱如何缓解？多地医疗机构试点免陪照护服务",
      "cover": "https://imgpai.thepaper.cn/newpai/image/1751236854437_6cx8Rd_1751236854729.png",
      "hot": 176,
      "timestamp": 1751238841655,
      "url": "https://www.thepaper.cn/newsDetail_forward_31064643",
      "mobileUrl": "https://m.thepaper.cn/newsDetail_forward_31064643"
    },
    {
      "id": "31049263",
      "title": "“离职博主”流量潮里，一个不想卷的英国人",
      "cover": "https://imgpai.thepaper.cn/newpai/image/1751022094063_xBsxWE_1751022094230.png",
      "hot": 139,
      "timestamp": 1751239484172,
      "url": "https://www.thepaper.cn/newsDetail_forward_31049263",
      "mobileUrl": "https://m.thepaper.cn/newsDetail_forward_31049263"
    }
  ]
}