{
  "meta": {
    "platform": "zhihu-daily",
    "date": "2025-09-22T01:28:22.685069",
    "count": 4
  },
  "data": [
    {
      "id": 9784144,
      "title": "40 年后，塔克拉玛干会变成绿洲吗？",
      "cover": "https://pica.zhimg.com/v2-fca9c53a066b1a99c526070eda4f914e.jpg?source=8673f162",
      "author": "于硕 · 4 分钟阅读",
      "url": "https://daily.zhihu.com/story/9784144",
      "mobileUrl": "https://daily.zhihu.com/story/9784144"
    },
    {
      "id": 9784150,
      "title": "为什么狮子老虎的眼睛和猫的眼睛不一样？",
      "cover": "https://picx.zhimg.com/v2-9884f37fb837abd06b02b53397f2d054.jpg?source=8673f162",
      "author": "剁椒鹿 · 3 分钟阅读",
      "url": "https://daily.zhihu.com/story/9784150",
      "mobileUrl": "https://daily.zhihu.com/story/9784150"
    },
    {
      "id": 9784151,
      "title": "人们在做梦的时候、喝醉的时候、脑力枯竭的时候，都是如何思考的？",
      "cover": "https://pic1.zhimg.com/v2-8ae73e9a5119e31e5add91da4b97edf6.jpg?source=8673f162",
      "author": "解磊 · 1 分钟阅读",
      "url": "https://daily.zhihu.com/story/9784151",
      "mobileUrl": "https://daily.zhihu.com/story/9784151"
    },
    {
      "id": 9784155,
      "title": "瞎扯 · 如何正确地吐槽",
      "cover": "https://picx.zhimg.com/v2-3cb34e5ef4a52b44ddf998748ef0b535.jpg?source=8673f162",
      "author": "VOL.3746",
      "url": "https://daily.zhihu.com/story/9784155",
      "mobileUrl": "https://daily.zhihu.com/story/9784155"
    }
  ]
}