{
  "meta": {
    "platform": "zhihu-daily",
    "date": "2025-12-24T01:42:05.231118",
    "count": 4
  },
  "data": [
    {
      "id": 9786278,
      "title": "有人认为寒潮能证明全球变暖是个骗局，这一观点有科学依据吗？",
      "cover": "https://picx.zhimg.com/v2-0b7ed6ee3374e1e7f687c6cdd7443686.jpg?source=8673f162",
      "author": "气象喵探员 · 6 分钟阅读",
      "hot": null,
      "timestamp": null,
      "url": "https://daily.zhihu.com/story/9786278",
      "mobileUrl": "https://daily.zhihu.com/story/9786278"
    },
    {
      "id": 9786269,
      "title": "兔子和老鼠都吃庄稼，为什么古代怕鼠患而不怕「兔患」呢？",
      "cover": "https://picx.zhimg.com/v2-03973e20353faf016d29118768b75178.jpg?source=8673f162",
      "author": "瞻云 · 4 分钟阅读",
      "hot": null,
      "timestamp": null,
      "url": "https://daily.zhihu.com/story/9786269",
      "mobileUrl": "https://daily.zhihu.com/story/9786269"
    },
    {
      "id": 9786275,
      "title": "为啥感觉现在苹果品种是红富士一统天下？",
      "cover": "https://picx.zhimg.com/v2-41aec54a445b96fbc6b2d230254170c9.jpg?source=8673f162",
      "author": "碗丸 · 8 分钟阅读",
      "hot": null,
      "timestamp": null,
      "url": "https://daily.zhihu.com/story/9786275",
      "mobileUrl": "https://daily.zhihu.com/story/9786275"
    },
    {
      "id": 9786097,
      "title": "瞎扯 · 如何正确地吐槽",
      "cover": "https://picx.zhimg.com/v2-3cb34e5ef4a52b44ddf998748ef0b535.jpg?source=8673f162",
      "author": "VOL.3809",
      "hot": null,
      "timestamp": null,
      "url": "https://daily.zhihu.com/story/9786097",
      "mobileUrl": "https://daily.zhihu.com/story/9786097"
    }
  ]
}