{
  "meta": {
    "platform": "douyin",
    "date": "2026-03-16T02:28:42.936150",
    "count": 20
  },
  "data": [
    {
      "id": "2431855",
      "title": "315曝光名单",
      "timestamp": 1773581812000,
      "hot": 11028413,
      "url": "https://www.douyin.com/hot/2431855",
      "mobileUrl": "https://www.douyin.com/hot/2431855"
    },
    {
      "id": "2431251",
      "title": "停下来是为了更好地出发",
      "timestamp": 1773546522000,
      "hot": 10952967,
      "url": "https://www.douyin.com/hot/2431251",
      "mobileUrl": "https://www.douyin.com/hot/2431251"
    },
    {
      "id": "2431824",
      "title": "加快场景培育开放和大规模应用",
      "timestamp": 1773579714000,
      "hot": 10816832,
      "url": "https://www.douyin.com/hot/2431824",
      "mobileUrl": "https://www.douyin.com/hot/2431824"
    },
    {
      "id": "2431516",
      "title": "315晚会",
      "timestamp": 1773560631000,
      "hot": 10736042,
      "url": "https://www.douyin.com/hot/2431516",
      "mobileUrl": "https://www.douyin.com/hot/2431516"
    },
    {
      "id": "2431635",
      "title": "中美经贸磋商开始举行",
      "timestamp": 1773565797000,
      "hot": 10198739,
      "url": "https://www.douyin.com/hot/2431635",
      "mobileUrl": "https://www.douyin.com/hot/2431635"
    },
    {
      "id": "2431401",
      "title": "俄方赞同中方对两国关系评价",
      "timestamp": 1773555386000,
      "hot": 10003138,
      "url": "https://www.douyin.com/hot/2431401",
      "mobileUrl": "https://www.douyin.com/hot/2431401"
    },
    {
      "id": "2431220",
      "title": "瓦列霍斯KO艾米特",
      "timestamp": 1773544775000,
      "hot": 8764342,
      "url": "https://www.douyin.com/hot/2431220",
      "mobileUrl": "https://www.douyin.com/hot/2431220"
    },
    {
      "id": "2431708",
      "title": "美宜佳门店被查获假烟上百万支",
      "timestamp": 1773570361000,
      "hot": 8749594,
      "url": "https://www.douyin.com/hot/2431708",
      "mobileUrl": "https://www.douyin.com/hot/2431708"
    },
    {
      "id": "2431465",
      "title": "刘文祥麻辣烫回应食材以次充好",
      "timestamp": 1773557862000,
      "hot": 7808887,
      "url": "https://www.douyin.com/hot/2431465",
      "mobileUrl": "https://www.douyin.com/hot/2431465"
    },
    {
      "id": "2430457",
      "title": "老爸评测净水器",
      "timestamp": 1773469592000,
      "hot": 7757481,
      "url": "https://www.douyin.com/hot/2430457",
      "mobileUrl": "https://www.douyin.com/hot/2430457"
    },
    {
      "id": "2431785",
      "title": "网红鸡爪用双氧水“漂白”",
      "timestamp": 1773576722000,
      "hot": 7756208,
      "url": "https://www.douyin.com/hot/2431785",
      "mobileUrl": "https://www.douyin.com/hot/2431785"
    },
    {
      "id": "2431520",
      "title": "警惕这些假冒的315查询网站",
      "timestamp": 1773560894000,
      "hot": 7755060,
      "url": "https://www.douyin.com/hot/2431520",
      "mobileUrl": "https://www.douyin.com/hot/2431520"
    },
    {
      "id": "2431673",
      "title": "随元青又准备去哪个村",
      "timestamp": 1773567720000,
      "hot": 7734581,
      "url": "https://www.douyin.com/hot/2431673",
      "mobileUrl": "https://www.douyin.com/hot/2431673"
    },
    {
      "id": "2431896",
      "title": "梦龙乐队巡演上海站",
      "timestamp": 1773584800000,
      "hot": 7731971,
      "url": "https://www.douyin.com/hot/2431896",
      "mobileUrl": "https://www.douyin.com/hot/2431896"
    },
    {
      "id": "2431717",
      "title": "谢征从随元青手上救下宁娘",
      "timestamp": 1773571144000,
      "hot": 7729964,
      "url": "https://www.douyin.com/hot/2431717",
      "mobileUrl": "https://www.douyin.com/hot/2431717"
    },
    {
      "id": "2431224",
      "title": "Cortis进行曲舞蹈挑战",
      "timestamp": 1773544984000,
      "hot": 7726610,
      "url": "https://www.douyin.com/hot/2431224",
      "mobileUrl": "https://www.douyin.com/hot/2431224"
    },
    {
      "id": "2431890",
      "title": "用灰太狼和表哥打开齐旻随元青",
      "timestamp": 1773584465000,
      "hot": 7715275,
      "url": "https://www.douyin.com/hot/2431890",
      "mobileUrl": "https://www.douyin.com/hot/2431890"
    },
    {
      "id": "2431948",
      "title": "马立奥人生第一次钢琴演奏会",
      "timestamp": 1773617356000,
      "hot": 7711330,
      "url": "https://www.douyin.com/hot/2431948",
      "mobileUrl": "https://www.douyin.com/hot/2431948"
    },
    {
      "id": "2431966",
      "title": "我家那一身反骨的猫咪",
      "timestamp": 1773618871000,
      "hot": 7693466,
      "url": "https://www.douyin.com/hot/2431966",
      "mobileUrl": "https://www.douyin.com/hot/2431966"
    },
    {
      "id": "2431693",
      "title": "我们两个都拉过勾",
      "timestamp": 1773568865000,
      "hot": 7690597,
      "url": "https://www.douyin.com/hot/2431693",
      "mobileUrl": "https://www.douyin.com/hot/2431693"
    }
  ]
}