{
  "meta": {
    "platform": "toutiao",
    "date": "2025-08-06T01:49:52.382090",
    "count": 20
  },
  "data": [
    {
      "id": "7534677521867489306",
      "title": "许家印香港大宅挖出464平“地牢”",
      "cover": "https://p3-sign.toutiaoimg.com/top-static-files-outer/breaknews/1fe02024-1617-4a92-858b-2639040d355a~tplv-tt-shrink:960:540.jpeg?_iz=30575&from=sign_default&lk3s=8d617dac&x-expires=1757030400&x-signature=5JKvOZneJqRGS91yI7kjU9q%2F7oM%3D",
      "timestamp": 7534677521867489000,
      "hot": 25306802,
      "url": "https://www.toutiao.com/trending/7534677521867489306/",
      "mobileUrl": "https://api.toutiaoapi.com/feoffline/amos_land/new/html/main/index.html?topic_id=7534677521867489306"
    },
    {
      "id": "7535068247004024356",
      "title": "“免一年幼儿园保教费”央地财政共担",
      "cover": "https://p3-sign.toutiaoimg.com/mosaic-legacy/2b29000036f8405561443~tplv-tt-shrink:960:540.jpeg?_iz=30575&from=sign_default&lk3s=8d617dac&x-expires=1757030400&x-signature=XXza9Ntxe7lakrp14YKCB%2FtJFNk%3D",
      "timestamp": 7535068247004025000,
      "hot": 22898542,
      "url": "https://www.toutiao.com/trending/7535068247004024356/",
      "mobileUrl": "https://api.toutiaoapi.com/feoffline/amos_land/new/html/main/index.html?topic_id=7535068247004024356"
    },
    {
      "id": "7534956615540850726",
      "title": "洪水退去 返家后这些细节要注意",
      "cover": "https://p3-sign.toutiaoimg.com/mosaic-legacy/2b29000036f8405561443~tplv-tt-shrink:960:540.jpeg?_iz=30575&from=sign_default&lk3s=8d617dac&x-expires=1757030400&x-signature=XXza9Ntxe7lakrp14YKCB%2FtJFNk%3D",
      "timestamp": 7534956615540851000,
      "hot": 20719457,
      "url": "https://www.toutiao.com/trending/7534956615540850726/",
      "mobileUrl": "https://api.toutiaoapi.com/feoffline/amos_land/new/html/main/index.html?topic_id=7534956615540850726"
    },
    {
      "id": "7534590071569072174",
      "title": "7月降水仅6毫米的河南驻马店下雨了",
      "cover": "https://p3-sign.toutiaoimg.com/mosaic-legacy/2b29000036f8405561443~tplv-tt-shrink:960:540.jpeg?_iz=30575&from=sign_default&lk3s=8d617dac&x-expires=1757030400&x-signature=XXza9Ntxe7lakrp14YKCB%2FtJFNk%3D",
      "timestamp": 7534590071569072000,
      "hot": 18747740,
      "url": "https://www.toutiao.com/trending/7534590071569072174/",
      "mobileUrl": "https://api.toutiaoapi.com/feoffline/amos_land/new/html/main/index.html?topic_id=7534590071569072174"
    },
    {
      "id": "7535028303095189042",
      "title": "公办幼儿园教师工资纳入财政保障",
      "cover": "https://p3-sign.toutiaoimg.com/mosaic-legacy/2b29000036f8405561443~tplv-tt-shrink:960:540.jpeg?_iz=30575&from=sign_default&lk3s=8d617dac&x-expires=1757030400&x-signature=XXza9Ntxe7lakrp14YKCB%2FtJFNk%3D",
      "timestamp": 7535028303095190000,
      "hot": 16963657,
      "url": "https://www.toutiao.com/trending/7535028303095189042/",
      "mobileUrl": "https://api.toutiaoapi.com/feoffline/amos_land/new/html/main/index.html?topic_id=7535028303095189042"
    },
    {
      "id": "7534891393488191527",
      "title": "被逼停摩托车主：不想追究了 太折腾",
      "cover": "https://p3-sign.toutiaoimg.com/tos-cn-i-qvj2lq49k0/beb6c0b0b6af4d46b69a3bd290648367~tplv-tt-shrink:960:540.jpeg?_iz=30575&from=sign_default&lk3s=8d617dac&x-expires=1757030400&x-signature=tUMqBFiK8N6dybnC41y7i%2F2Jx%2BE%3D",
      "timestamp": 7534891393488191000,
      "hot": 15349351,
      "url": "https://www.toutiao.com/trending/7534891393488191527/",
      "mobileUrl": "https://api.toutiaoapi.com/feoffline/amos_land/new/html/main/index.html?topic_id=7534891393488191527"
    },
    {
      "id": "7535000730747502643",
      "title": "英52岁女子称在空中遭滑翔伞教练性侵",
      "cover": "https://p3-sign.toutiaoimg.com/tos-cn-i-qvj2lq49k0/8eeb606e99354fb8866ac8ea39806dd0~tplv-tt-shrink:960:540.jpeg?_iz=30575&from=sign_default&lk3s=8d617dac&x-expires=1757030400&x-signature=AexGcavTJFWs%2FZ0tx5AHoADapVQ%3D",
      "timestamp": 7535000730747503000,
      "hot": 13888667,
      "url": "https://www.toutiao.com/trending/7535000730747502643/",
      "mobileUrl": "https://api.toutiaoapi.com/feoffline/amos_land/new/html/main/index.html?topic_id=7535000730747502643"
    },
    {
      "id": "7535242167573286439",
      "title": "广东这次暴雨为何这么厉害",
      "cover": "https://p3-sign.toutiaoimg.com/tos-cn-i-qvj2lq49k0/6fe99b2c592040328436dc2885a9e02f~tplv-tt-shrink:960:540.jpeg?_iz=30575&from=sign_default&lk3s=8d617dac&x-expires=1757030400&x-signature=hBuebBvbIV6ABnIHloJ9CQ0baBw%3D",
      "timestamp": 7535242167573287000,
      "hot": 12566986,
      "url": "https://www.toutiao.com/trending/7535242167573286439/",
      "mobileUrl": "https://api.toutiaoapi.com/feoffline/amos_land/new/html/main/index.html?topic_id=7535242167573286439"
    },
    {
      "id": "7535251886761594377",
      "title": "以总理决定全面占领加沙",
      "cover": "https://p3-sign.toutiaoimg.com/tos-cn-i-qvj2lq49k0/60235bedda424e16b472345434458532~tplv-tt-shrink:960:540.jpeg?_iz=30575&from=sign_default&lk3s=8d617dac&x-expires=1757030400&x-signature=NUo%2FyXq7pcEFp9zScBj1otJQevE%3D",
      "timestamp": 7535251886761595000,
      "hot": 11371079,
      "url": "https://www.toutiao.com/trending/7535251886761594377/",
      "mobileUrl": "https://api.toutiaoapi.com/feoffline/amos_land/new/html/main/index.html?topic_id=7535251886761594377"
    },
    {
      "id": "7534143953911201855",
      "title": "“大同地震现场一片废墟”不实",
      "cover": "https://p3-sign.toutiaoimg.com/tos-cn-i-qvj2lq49k0/4cb381c8302a46f3ad0d946825bdbd2f~tplv-tt-shrink:960:540.jpeg?_iz=30575&from=sign_default&lk3s=8d617dac&x-expires=1757030400&x-signature=WsmnRye1EQzcEQ%2BX3LlmxKddmUQ%3D",
      "timestamp": 7534143953911202000,
      "hot": 10288978,
      "url": "https://www.toutiao.com/trending/7534143953911201855/",
      "mobileUrl": "https://api.toutiaoapi.com/feoffline/amos_land/new/html/main/index.html?topic_id=7534143953911201855"
    },
    {
      "id": "7535046465362611731",
      "title": "《东极岛》上映后你会去看吗",
      "cover": "https://p3-sign.toutiaoimg.com/tos-cn-i-qvj2lq49k0/8202ad33b60443cf997054cf4c96f3d2~tplv-tt-shrink:960:540.jpeg?_iz=30575&from=sign_default&lk3s=8d617dac&x-expires=1757030400&x-signature=aUrs8nJslJc53qq5imuzZ7aFX78%3D",
      "timestamp": 7535046465362612000,
      "hot": 9309852,
      "url": "https://www.toutiao.com/trending/7535046465362611731/",
      "mobileUrl": "https://api.toutiaoapi.com/feoffline/amos_land/new/html/main/index.html?topic_id=7535046465362611731"
    },
    {
      "id": "7534934336261406774",
      "title": "羊水栓塞为何死亡率极高",
      "cover": "https://p3-sign.toutiaoimg.com/mosaic-legacy/2b29000036f8405561443~tplv-tt-shrink:960:540.jpeg?_iz=30575&from=sign_default&lk3s=8d617dac&x-expires=1757030400&x-signature=XXza9Ntxe7lakrp14YKCB%2FtJFNk%3D",
      "timestamp": 7534934336261407000,
      "hot": 8423902,
      "url": "https://www.toutiao.com/trending/7534934336261406774/",
      "mobileUrl": "https://api.toutiaoapi.com/feoffline/amos_land/new/html/main/index.html?topic_id=7534934336261406774"
    },
    {
      "id": "7535155373519487039",
      "title": "中国男篮亚洲杯首战力克东道主",
      "cover": "https://p3-sign.toutiaoimg.com/tos-cn-i-qvj2lq49k0/d4bb4be8ba3c497ba954f1fc539ad281~tplv-tt-shrink:960:540.jpeg?_iz=30575&from=sign_default&lk3s=8d617dac&x-expires=1757030400&x-signature=r%2F30Wo9gameUIFyWpfmWfbsMsNM%3D",
      "timestamp": 7535155373519487000,
      "hot": 7622262,
      "url": "https://www.toutiao.com/trending/7535155373519487039/",
      "mobileUrl": "https://api.toutiaoapi.com/feoffline/amos_land/new/html/main/index.html?topic_id=7535155373519487039"
    },
    {
      "id": "7535000270481211418",
      "title": "暴雨致街道被淹 眼镜蛇缠在窗户上",
      "cover": "https://p3-sign.toutiaoimg.com/tos-cn-i-qvj2lq49k0/e26d2f9d494f46d2aa2fe0a6f0dabd5f~tplv-tt-shrink:960:540.jpeg?_iz=30575&from=sign_default&lk3s=8d617dac&x-expires=1757030400&x-signature=ROUVBkU47GmR05OW6sblF5QonSQ%3D",
      "timestamp": 7535000270481211000,
      "hot": 6896908,
      "url": "https://www.toutiao.com/trending/7535000270481211418/",
      "mobileUrl": "https://api.toutiaoapi.com/feoffline/amos_land/new/html/main/index.html?topic_id=7535000270481211418"
    },
    {
      "id": "7535094634532310569",
      "title": "一口气看懂免除保教费政策",
      "cover": "https://p3-sign.toutiaoimg.com/tos-cn-i-qvj2lq49k0/a5d75e05229d4ba595838b0d523b20d2~tplv-tt-shrink:960:540.jpeg?_iz=30575&from=sign_default&lk3s=8d617dac&x-expires=1757030400&x-signature=xAWkXptq5JT4dHdqxSVdtyRKiTc%3D",
      "timestamp": 7535094634532311000,
      "hot": 6240580,
      "url": "https://www.toutiao.com/trending/7535094634532310569/",
      "mobileUrl": "https://api.toutiaoapi.com/feoffline/amos_land/new/html/main/index.html?topic_id=7535094634532310569"
    },
    {
      "id": "7534904222177824292",
      "title": "你支持取消车辆年检吗",
      "cover": "https://p3-sign.toutiaoimg.com/mosaic-legacy/2b28f000370774e5fabc5~tplv-tt-shrink:960:540.jpeg?_iz=30575&from=sign_default&lk3s=8d617dac&x-expires=1757030400&x-signature=2oeau8Cdonrcneq5Yx1LjXee0WM%3D",
      "timestamp": 7534904222177825000,
      "hot": 5646710,
      "url": "https://www.toutiao.com/trending/7534904222177824292/",
      "mobileUrl": "https://api.toutiaoapi.com/feoffline/amos_land/new/html/main/index.html?topic_id=7534904222177824292"
    },
    {
      "id": "7534521701682462756",
      "title": "车库即将被淹 众人齐心筑起挡水坝",
      "cover": "https://p3-sign.toutiaoimg.com/tos-cn-i-qvj2lq49k0/c818c0fb052f451d95161f114c66e06b~tplv-tt-shrink:960:540.jpeg?_iz=30575&from=sign_default&lk3s=8d617dac&x-expires=1757030400&x-signature=UdHyhSLjkkRFk5enMfgdk8a4NDw%3D",
      "timestamp": 7534521701682463000,
      "hot": 5109355,
      "url": "https://www.toutiao.com/trending/7534521701682462756/",
      "mobileUrl": "https://api.toutiaoapi.com/feoffline/amos_land/new/html/main/index.html?topic_id=7534521701682462756"
    },
    {
      "id": "7534963851867983423",
      "title": "学者：梅德韦杰夫“祸从口出”",
      "cover": "https://p3-sign.toutiaoimg.com/tos-cn-i-qvj2lq49k0/56f1f44fca7c40558b6fa243331dde0f~tplv-tt-shrink:960:540.jpeg?_iz=30575&from=sign_default&lk3s=8d617dac&x-expires=1757030400&x-signature=cTGEhiZ9tw6aTqxPSHdFgpT%2FwF4%3D",
      "timestamp": 7534963851867984000,
      "hot": 4623135,
      "url": "https://www.toutiao.com/trending/7534963851867983423/",
      "mobileUrl": "https://api.toutiaoapi.com/feoffline/amos_land/new/html/main/index.html?topic_id=7534963851867983423"
    },
    {
      "id": "7535023272161837107",
      "title": "霍启刚逛新疆国际大巴扎被偶遇",
      "cover": "https://p3-sign.toutiaoimg.com/mosaic-legacy/2b29000036f8405561443~tplv-tt-shrink:960:540.jpeg?_iz=30575&from=sign_default&lk3s=8d617dac&x-expires=1757030400&x-signature=XXza9Ntxe7lakrp14YKCB%2FtJFNk%3D",
      "timestamp": 7535023272161837000,
      "hot": 4183186,
      "url": "https://www.toutiao.com/trending/7535023272161837107/",
      "mobileUrl": "https://api.toutiaoapi.com/feoffline/amos_land/new/html/main/index.html?topic_id=7535023272161837107"
    },
    {
      "id": "7533970671681077299",
      "title": "交警回应车主逆行插队扬言弄死阻拦者",
      "cover": "https://p3-sign.toutiaoimg.com/tos-cn-i-qvj2lq49k0/f00c6c3d653a4d5f881c43e1870875b3~tplv-tt-shrink:960:540.jpeg?_iz=30575&from=sign_default&lk3s=8d617dac&x-expires=1757030400&x-signature=Hk3dYvqfoBCdTNkViUmR6Wi2MS4%3D",
      "timestamp": 7533970671681077000,
      "hot": 3785103,
      "url": "https://www.toutiao.com/trending/7533970671681077299/",
      "mobileUrl": "https://api.toutiaoapi.com/feoffline/amos_land/new/html/main/index.html?topic_id=7533970671681077299"
    }
  ]
}