{
  "meta": {
    "platform": "toutiao",
    "date": "2025-09-24T01:26:38.856694",
    "count": 20
  },
  "data": [
    {
      "id": "7553212757827538495",
      "title": "24小时直击超强台风桦加沙",
      "cover": "https://p3-sign.toutiaoimg.com/mosaic-legacy/2b29000036f8405561443~tplv-tt-shrink:960:540.jpeg?_iz=30575&from=sign_default&lk3s=8d617dac&x-expires=1761264000&x-signature=Cml5nb6xSldycRESmf%2FUhXQ77Y8%3D",
      "timestamp": 7553212757827539000,
      "hot": 68641336,
      "url": "https://www.toutiao.com/trending/7553212757827538495/",
      "mobileUrl": "https://api.toutiaoapi.com/feoffline/amos_land/new/html/main/index.html?topic_id=7553212757827538495"
    },
    {
      "id": "7552143781387829311",
      "title": "美媒：美大豆收获季中国订购量仍为零",
      "cover": "https://p3-sign.toutiaoimg.com/tos-cn-i-qvj2lq49k0/9605a581cd71482897e01049ae24ddb7~tplv-tt-shrink:960:540.jpeg?_iz=30575&from=sign_default&lk3s=8d617dac&x-expires=1761264000&x-signature=FsoRzZgoS%2FXuvSBvB%2F5RzFfL6KU%3D",
      "timestamp": 7552143781387829000,
      "hot": 62109249,
      "url": "https://www.toutiao.com/trending/7552143781387829311/",
      "mobileUrl": "https://api.toutiaoapi.com/feoffline/amos_land/new/html/main/index.html?topic_id=7552143781387829311"
    },
    {
      "id": "7553212609819033641",
      "title": "丰收背后的“芯片密码”",
      "cover": "https://p3-sign.toutiaoimg.com/tos-cn-i-qvj2lq49k0/ae1f04bf68b5412bb300230215f484e5~tplv-tt-shrink:960:540.jpeg?_iz=30575&from=sign_default&lk3s=8d617dac&x-expires=1761264000&x-signature=S6trxHhnZKbJaZ%2BZCpR1rohlMnA%3D",
      "timestamp": 7553212609819034000,
      "hot": 56198773,
      "url": "https://www.toutiao.com/trending/7553212609819033641/",
      "mobileUrl": "https://api.toutiaoapi.com/feoffline/amos_land/new/html/main/index.html?topic_id=7553212609819033641"
    },
    {
      "id": "7553120563674218550",
      "title": "媒体：中欧班列明日恢复通行",
      "cover": "https://p3-sign.toutiaoimg.com/tos-cn-i-qvj2lq49k0/9d0382c441354595b3b1d063f289423a~tplv-tt-shrink:960:540.jpeg?_iz=30575&from=sign_default&lk3s=8d617dac&x-expires=1761264000&x-signature=CxcXG2C8fTXieqaCrwPebXNU4%2FQ%3D",
      "timestamp": 7553120563674218000,
      "hot": 50850752,
      "url": "https://www.toutiao.com/trending/7553120563674218550/",
      "mobileUrl": "https://api.toutiaoapi.com/feoffline/amos_land/new/html/main/index.html?topic_id=7553120563674218550"
    },
    {
      "id": "7553435196462255643",
      "title": "深圳巨浪如排山倒海 香港高楼晃动",
      "cover": "https://p3-sign.toutiaoimg.com/tos-cn-i-qvj2lq49k0/d89693f8051e4b17a7c08c31f503079a~tplv-tt-shrink:960:540.jpeg?_iz=30575&from=sign_default&lk3s=8d617dac&x-expires=1761264000&x-signature=c%2FkIyQn%2BJBn6mgSZMiKCBL4igFk%3D",
      "timestamp": 7553435196462256000,
      "hot": 46011663,
      "url": "https://www.toutiao.com/trending/7553435196462255643/",
      "mobileUrl": "https://api.toutiaoapi.com/feoffline/amos_land/new/html/main/index.html?topic_id=7553435196462255643"
    },
    {
      "id": "7553300755093684270",
      "title": "特朗普联大演讲滚梯卡住提词器坏了",
      "cover": "https://p26-sign.toutiaoimg.com/mosaic-legacy/2b29000036f8405561443~tplv-tt-shrink:960:540.jpeg?_iz=30575&from=sign_default&lk3s=8d617dac&x-expires=1761264000&x-signature=yKcqG6GAMlSuDioQ3DEWrgJLwAo%3D",
      "timestamp": 7553300755093684000,
      "hot": 41633075,
      "url": "https://www.toutiao.com/trending/7553300755093684270/",
      "mobileUrl": "https://api.toutiaoapi.com/feoffline/amos_land/new/html/main/index.html?topic_id=7553300755093684270"
    },
    {
      "id": "7553425087530012202",
      "title": "学者：福建舰三型机弹射证明中国速度",
      "cover": "https://p3-sign.toutiaoimg.com/tos-cn-i-qvj2lq49k0/fd536254113b4a4f88cfcf3afcac2cf6~tplv-tt-shrink:960:540.jpeg?_iz=30575&from=sign_default&lk3s=8d617dac&x-expires=1761264000&x-signature=tMzBiyZ3I%2FN7UcRkuPi9wQ89Ci8%3D",
      "timestamp": 7553425087530013000,
      "hot": 37671164,
      "url": "https://www.toutiao.com/trending/7553425087530012202/",
      "mobileUrl": "https://api.toutiaoapi.com/feoffline/amos_land/new/html/main/index.html?topic_id=7553425087530012202"
    },
    {
      "id": "7553448731060981298",
      "title": "台风“桦加沙”已致台湾14人死亡",
      "cover": "https://p3-sign.toutiaoimg.com/mosaic-legacy/2b29000036f8405561443~tplv-tt-shrink:960:540.jpeg?_iz=30575&from=sign_default&lk3s=8d617dac&x-expires=1761264000&x-signature=Cml5nb6xSldycRESmf%2FUhXQ77Y8%3D",
      "timestamp": 7553448731060982000,
      "hot": 34086278,
      "url": "https://www.toutiao.com/trending/7553448731060981298/",
      "mobileUrl": "https://api.toutiaoapi.com/feoffline/amos_land/new/html/main/index.html?topic_id=7553448731060981298"
    },
    {
      "id": "7552864244677853226",
      "title": "“风王”桦加沙来临前的广州",
      "cover": "https://p6-sign.toutiaoimg.com/tos-cn-i-qvj2lq49k0/e51ccb7fa8e34f8aa2071b9aab3ed11b~tplv-tt-shrink:960:540.jpeg?_iz=30575&from=sign_default&lk3s=8d617dac&x-expires=1761264000&x-signature=D8sXeDlOkSPPkivfXRuBcZzzdR0%3D",
      "timestamp": 7552864244677853000,
      "hot": 30842540,
      "url": "https://www.toutiao.com/trending/7552864244677853226/",
      "mobileUrl": "https://api.toutiaoapi.com/feoffline/amos_land/new/html/main/index.html?topic_id=7552864244677853226"
    },
    {
      "id": "7553204503496163337",
      "title": "孩子长高就要大量吃肉？不实",
      "cover": "https://p3-sign.toutiaoimg.com/tos-cn-i-qvj2lq49k0/7467c30465f545d89133099a880ae4dc~tplv-tt-shrink:960:540.jpeg?_iz=30575&from=sign_default&lk3s=8d617dac&x-expires=1761264000&x-signature=6D9G6VXG5jFlmk4okMNJsIeId4U%3D",
      "timestamp": 7553204503496163000,
      "hot": 27907484,
      "url": "https://www.toutiao.com/trending/7553204503496163337/",
      "mobileUrl": "https://api.toutiaoapi.com/feoffline/amos_land/new/html/main/index.html?topic_id=7553204503496163337"
    },
    {
      "id": "7553343155702136886",
      "title": "如何看待特朗普与古特雷斯的分歧",
      "cover": "https://p3-sign.toutiaoimg.com/tos-cn-i-qvj2lq49k0/1ef2764911594770a69dbb651475e4ed~tplv-tt-shrink:960:540.jpeg?_iz=30575&from=sign_default&lk3s=8d617dac&x-expires=1761264000&x-signature=1Ze4STQvf5yHqEb%2BZ9FxJy5hoBU%3D",
      "timestamp": 7553343155702137000,
      "hot": 25251736,
      "url": "https://www.toutiao.com/trending/7553343155702136886/",
      "mobileUrl": "https://api.toutiaoapi.com/feoffline/amos_land/new/html/main/index.html?topic_id=7553343155702136886"
    },
    {
      "id": "7552911760854106148",
      "title": "广东省委书记：决战就在眼前",
      "cover": "https://p3-sign.toutiaoimg.com/mosaic-legacy/2b29000036f8405561443~tplv-tt-shrink:960:540.jpeg?_iz=30575&from=sign_default&lk3s=8d617dac&x-expires=1761264000&x-signature=Cml5nb6xSldycRESmf%2FUhXQ77Y8%3D",
      "timestamp": 7552911760854106000,
      "hot": 22848716,
      "url": "https://www.toutiao.com/trending/7552911760854106148/",
      "mobileUrl": "https://api.toutiaoapi.com/feoffline/amos_land/new/html/main/index.html?topic_id=7552911760854106148"
    },
    {
      "id": "7553182200607735827",
      "title": "预计广州10级以上大风将持续12小时",
      "cover": "https://p3-sign.toutiaoimg.com/tos-cn-i-qvj2lq49k0/15014295bafc482e8d41ef44b78a08c2~tplv-tt-shrink:960:540.jpeg?_iz=30575&from=sign_default&lk3s=8d617dac&x-expires=1761264000&x-signature=5q%2BbBBl2sSoTfjg6icHI%2B43CqyY%3D",
      "timestamp": 7553182200607736000,
      "hot": 20674373,
      "url": "https://www.toutiao.com/trending/7553182200607735827/",
      "mobileUrl": "https://api.toutiaoapi.com/feoffline/amos_land/new/html/main/index.html?topic_id=7553182200607735827"
    },
    {
      "id": "7553209826621394468",
      "title": "特朗普称其重返白宫后已结束7场战争",
      "cover": "https://p3-sign.toutiaoimg.com/tos-cn-i-qvj2lq49k0/7c92b796bf0446a28f420ed412d562d8~tplv-tt-shrink:960:540.jpeg?_iz=30575&from=sign_default&lk3s=8d617dac&x-expires=1761264000&x-signature=BmaofvcaCoezA%2B7QER3NZKIp5XQ%3D",
      "timestamp": 7553209826621395000,
      "hot": 18706946,
      "url": "https://www.toutiao.com/trending/7553209826621394468/",
      "mobileUrl": "https://api.toutiaoapi.com/feoffline/amos_land/new/html/main/index.html?topic_id=7553209826621394468"
    },
    {
      "id": "7553093533155704874",
      "title": "台风来临时你见过啥天象",
      "cover": "https://p3-sign.toutiaoimg.com/tos-cn-i-qvj2lq49k0/81a3964247a84f03b5eca9544a707a53~tplv-tt-shrink:960:540.jpeg?_iz=30575&from=sign_default&lk3s=8d617dac&x-expires=1761264000&x-signature=ITn8%2F3facdonqcUmn9cswLkbis0%3D",
      "timestamp": 7553093533155705000,
      "hot": 16926745,
      "url": "https://www.toutiao.com/trending/7553093533155704874/",
      "mobileUrl": "https://api.toutiaoapi.com/feoffline/amos_land/new/html/main/index.html?topic_id=7553093533155704874"
    },
    {
      "id": "7553110407586516523",
      "title": "中欧北极快航开通",
      "cover": "https://p3-sign.toutiaoimg.com/mosaic-legacy/2b29000036f8405561443~tplv-tt-shrink:960:540.jpeg?_iz=30575&from=sign_default&lk3s=8d617dac&x-expires=1761264000&x-signature=Cml5nb6xSldycRESmf%2FUhXQ77Y8%3D",
      "timestamp": 7553110407586517000,
      "hot": 15315952,
      "url": "https://www.toutiao.com/trending/7553110407586516523/",
      "mobileUrl": "https://api.toutiaoapi.com/feoffline/amos_land/new/html/main/index.html?topic_id=7553110407586516523"
    },
    {
      "id": "7553209826621427236",
      "title": "特朗普：我该拿诺贝尔和平奖",
      "cover": "https://p3-sign.toutiaoimg.com/tos-cn-i-qvj2lq49k0/26057bad57cd4a43935e5df4ca042f44~tplv-tt-shrink:960:540.jpeg?_iz=30575&from=sign_default&lk3s=8d617dac&x-expires=1761264000&x-signature=zxcBBLjSYB34LRQbozmpkGgyMTQ%3D",
      "timestamp": 7553209826621428000,
      "hot": 13858446,
      "url": "https://www.toutiao.com/trending/7553209826621427236/",
      "mobileUrl": "https://api.toutiaoapi.com/feoffline/amos_land/new/html/main/index.html?topic_id=7553209826621427236"
    },
    {
      "id": "7553251436952289290",
      "title": "广东店主砌1米2砖墙防台风",
      "cover": "https://p3-sign.toutiaoimg.com/tos-cn-i-qvj2lq49k0/c74d26d92e4b4af7ab756113d0d33412~tplv-tt-shrink:960:540.jpeg?_iz=30575&from=sign_default&lk3s=8d617dac&x-expires=1761264000&x-signature=qpu1z%2FMYjkAzU%2BSCdVKM0Qd3%2Boc%3D",
      "timestamp": 7553251436952289000,
      "hot": 12539641,
      "url": "https://www.toutiao.com/trending/7553251436952289290/",
      "mobileUrl": "https://api.toutiaoapi.com/feoffline/amos_land/new/html/main/index.html?topic_id=7553251436952289290"
    },
    {
      "id": "7553424136563854874",
      "title": "为何说西方承认巴勒斯坦国没这么简单",
      "cover": "https://p3-sign.toutiaoimg.com/mosaic-legacy/2b28f000370774e5fabc5~tplv-tt-shrink:960:540.jpeg?_iz=30575&from=sign_default&lk3s=8d617dac&x-expires=1761264000&x-signature=8Gn9Sgt7GnYLXgO8oYwZYlII5hY%3D",
      "timestamp": 7553424136563855000,
      "hot": 11346336,
      "url": "https://www.toutiao.com/trending/7553424136563854874/",
      "mobileUrl": "https://api.toutiaoapi.com/feoffline/amos_land/new/html/main/index.html?topic_id=7553424136563854874"
    },
    {
      "id": "7553424622813711935",
      "title": "特朗普57分钟联大演讲说了啥",
      "cover": "https://p3-sign.toutiaoimg.com/mosaic-legacy/2b29000036f8405561443~tplv-tt-shrink:960:540.jpeg?_iz=30575&from=sign_default&lk3s=8d617dac&x-expires=1761264000&x-signature=Cml5nb6xSldycRESmf%2FUhXQ77Y8%3D",
      "timestamp": 7553424622813712000,
      "hot": 10266589,
      "url": "https://www.toutiao.com/trending/7553424622813711935/",
      "mobileUrl": "https://api.toutiaoapi.com/feoffline/amos_land/new/html/main/index.html?topic_id=7553424622813711935"
    }
  ]
}