{
  "meta": {
    "platform": "jianshu",
    "date": "2026-03-28T02:09:42.959949",
    "count": 5
  },
  "data": [
    {
      "id": "3e8422fe93f9",
      "title": "坚持三个月",
      "desc": "我实在想不明白，为什么我面试了那么多家，都不成功，难道是形象，气质？也没有问题呀!  我平时面试，就穿着白衣黑裤，与面试官谈话也很流畅，可就...",
      "author": "梅兰之佳",
      "hot": null,
      "timestamp": null,
      "url": "https://www.jianshu.com/p/3e8422fe93f9",
      "mobileUrl": "https://www.jianshu.com/p/3e8422fe93f9"
    },
    {
      "id": "4c86c5e8423b",
      "title": "《40岁的尴尬》",
      "desc": "不知道是大数据推流还是其他什么原因。这两天看了好几篇四十岁的求职尴尬，甚至直接招聘要求是“不建议大龄应聘”，有一种赤果果的求职歧视，不禁想知道其...",
      "author": "黄秋秋",
      "hot": null,
      "timestamp": null,
      "url": "https://www.jianshu.com/p/4c86c5e8423b",
      "mobileUrl": "https://www.jianshu.com/p/4c86c5e8423b"
    },
    {
      "id": "b48b49947743",
      "title": "WCBA季后赛：张茹三大国手对决，35分惨败国手6中0，外援16中2",
      "desc": "WCBA季后赛首场比赛排名榜首的山西队对阵排名第八的武汉队，这场比赛两队都拥有国手级别球员，山西队拥有张茹、陈玉婕，武汉队则拥有联赛场均11.7...",
      "author": "体娱荒原",
      "hot": null,
      "timestamp": null,
      "url": "https://www.jianshu.com/p/b48b49947743",
      "mobileUrl": "https://www.jianshu.com/p/b48b49947743"
    },
    {
      "id": "d72d19546fdc",
      "title": "《红楼梦》审美|草蛇灰线，伏脉千里—《红楼梦》的结构美学与宿命闭环",
      "desc": "《红楼梦》之所以被公认为中国古典小说不可逾越的高峰，不仅在于其人物之鲜活、语言之诗化、意境之空灵、细节之精微，更在于它拥有中国文学史上最精密、最...",
      "author": "梅美生活",
      "hot": null,
      "timestamp": null,
      "url": "https://www.jianshu.com/p/d72d19546fdc",
      "mobileUrl": "https://www.jianshu.com/p/d72d19546fdc"
    },
    {
      "id": "2ba23c4925bc",
      "title": "以“锂”争上游之心，行“碳”索未来之程——青岛农业大学实践团完成淄博支教并走进博物馆",
      "cover": "https://upload-images.jianshu.io/upload_images/31012394-4c28cc5a9955e717.jpeg?x-oss-process=image/resize,w_360,h_240",
      "desc": "（刘娅伟 2026年2月13日） 2月12日，青岛农业大学“锌”火相传小小化学家“锂”争上游“碳”索未来赴淄博社会实践团在张店区东方社区支教的最...",
      "author": "书77",
      "hot": null,
      "timestamp": null,
      "url": "https://www.jianshu.com/p/2ba23c4925bc",
      "mobileUrl": "https://www.jianshu.com/p/2ba23c4925bc"
    }
  ]
}